Workbook

Sheet Cover Page
C10: BD (BDX) Valuation - Group 23
C12: Table of Contents: | G12: Analysts:
C13: Sheet 1: Assumptions Explanation | G13: Arisa Akiyama 1005763238
C14: Sheet 2: Inputs | G14: Sahand Davari 1007130230
C15: Sheet 3: Historical Analysis | G15: Majd Hijazi 1005691020
C16: Sheet 4: Revenue Model | G16: Victoria Magowan 1005152521
C17: Sheet 5: DCF Valuation | G17: Zhenyu Wang 1007072089
C18: Sheet 6: Comparables | G18: Yuchen Zhang 1005727830
C19: Sheet 7: BD Debt
C20: Sheet 8: Cost of Debt
C21: Sheet 9: Cost of Equity
C22: Sheet 10: WACC
C23: Sheet 11-14: BD Financials

Sheet Assumptions Explanation
A1: Ref. # | B1: Explanation of Assumption
A2: 1 | B2: The revenue growth rate is based on each segment's historical growth rate subject to adjustments based on current market conditions and future prospects.
A3: =A2+1 -> 2 | B3: COGS as % of revenue is used in our model since it is relatively stable over the years and it is highly correlated with revenue. There are significant inflation pressures which are expected to increase the prices of raw materials. It is also stated in BD's 2021 Annual Report that costs of raw materials, transportation, construction and other necessary costs for production and distribution of products have increased significantly. These pressures on its supply chain are expected to continue to increase. Therefore, we have adjusted the COGS as a % of revenue to be 3% higher than the historical average from 2016-2021. (BD Annual Report 2021 page 15)
A4: =A3+1 -> 3 | B4: OpEx as % of revenue is used in our model since it is relatively stable over the years and it is highly correlated with revenue. We then adjusted the cost to be a higher percentage as BD's costs are anticipated to increase. Firstly, the EU has recently adopted the EU Medical Device Regulation and the In Vitro Diagnostic Regulation which impose strict requirements for the marketing and sale of medical devices. Compliance and maintenance of medical devices subject to these regulations will increase operating expenses (BD Annual Report 2021 page 18). As mentioned in assumption 2, BD is subject to high inflation pressures which are expected to increase its operating expenses. In addition, the higher transportation and shipping costs as outlined in assumption 2 are expected to increase selling and administrative expenses. Overall, to account for these inflationary pressures on BD's costs, we have increased the OpEx as a % of revenues by 4% compared to the historical average.
A5: =A4+1 -> 4 | B5: D&A as % of revenue is used in our model since it is relatively stable over the years and D&A has a higher correlation with revenue compared to Net PPE.
A6: =A5+1 -> 5 | B6: Statutory US tax rate in 2021 is 21%.
A7: =A6+1 -> 6 | B7: The effective tax rate is much lower than federal statutory tax rate each year due to different foreign income tax on its foreign income (See BD Annual Report 2021 Note 16 - Income Taxes pg 99 and BD Annual Report 2018 Note 16 - Income Taxes pg 97). Since there is very high variability in the effective tax rate and we cannot reasonably predict the changes in the tax rates for each foreign country that BD operates in, we assume the US statutory tax rate of 21%.
A8: =A7+1 -> 7 | B8: It is more reasonable to use change in NWC as a % of revenue since the annual growth rate is very volatile with a high standard deviation.
A9: =A8+1 -> 8 | B9: CAPEX as % of revenue is used in our model since it is relatively stable over the years and it is highly correlated with revenue. We increased CAPEX as a % of revenue by 2% of the previous year as the CAPEX has been increasing each year from 2016 to 2021, with the exception of 2020 which was affected by the COVID-19 pandemic. Furthermore, management has expressed its strategy of geographic expansion which supports our assumption. (BD Annual Report 2021 page 39)
A10: =A9+1 -> 9 | B10: Increased revenue growth by .25 percentage points in bull case supported by an increase in the aging baby boomer population, an increase in chronic disease prevalence, and an assumed increase in elective procesures as virus eliminates all increasing demand.
A11: =A10+1 -> 10 | B11: COGS as % of revenue in the Bull case is decreased by 1 percentage point as supported in the company successfully cutting manufacturing and supplier costs.
A12: =A11+1 -> 11 | B12: OpEx as a % of revenue in the Bull case decreases by 1 percentage point as supported in successfully cutting operational expenses.
A13: =A12+1 -> 12 | B13: We assume that D&A as a % of revenue decreases in the Bull case by one percentage point.
A14: =A13+1 -> 13 | B14: We assume that CAPEX as a % of revenue in the Bull case decreases by 0.2 percentage points. We adjust for a small decrease as we believe that it is unlikely that the firm will decrease capital expenditures based on its increased spending on capital expenditures in the past few years.
... A26: =A25+1 -> 25 | B26: For the BD Interventional Segment, the average of the historical annual revenue growth rate is used as the base for our projections of the annual growth rate in the next five years. However, we remove the annual growth rate in 2019 as it reflects an inflated increase due to the inclusion of revenues from a new acquisition (BD Annual Report 2019 page 28). We believe this segment will continue to grow as the company has invested a consistent amount as capital expenditures into this segment with $120 million, $119 million, and $125million in FY2019, FY2020, and FY2021 respectively (BD Annual Report 2021 page 76). We did not adjust for COVID-19 impacts on revenues as the decrease in the growth rate in 2020 due to COVID-19 related pressures is offset by the increase in the growth rate in FY2021.
A27: =A26+1 -> 26 | B27: We assumed that the terminal growth rate is 2% with a conservative estimate aligned with the target inflation rate of the Federal Reserve . This is below the historical average GDP growth rate of around 3.14% from 1948 until 2021. | C27: https://ycharts.com/indicators/us_inflation_rate
A28: =A27+1 -> 27 | B28: Since the cash flows are discounted to the fiscal year end of the company of September 31, 2021 under our DCF model, we adjust the discounted time period to discount back to January 24, 2022. | C28: https://tradingeconomics.com/united-states/gdp-growth-annual#:~:text=GDP%20Annual%20Growth%20Rate%20in,the%20second%20quarter%20of%202020.
A29: =A28+1 -> 28 | B29: Located comparable companies through Factset, filtering through General Medical Devices in the North American region, with market caps over 10,000,000
A30: =A29+1 -> 29 | B30: Benchmark 10 year American treasury yield as of March 25th, 2022. (see screenshort below) | C30: https://www.bloomberg.com/markets/rates-bonds/government-bonds/us
A31: =A30+1 -> 30 | B31: Risk premium in the US has an average of 5.5% in 2021, where the historical average has been between 5.2%-5.7%. Thus, we believe that a 5.5% estimate is reasonable. | C31: https://www.statista.com/statistics/664840/average-market-risk-premium-usa/#:~:text=The%20average%20market%20risk%20premium,and%205.7%20percent%20since%202011.

Sheet Inputs
B2: Case Number | C2: ='DCF Valuation'!C3 -> 1 | D2: *Linked to "DCF Valuation"
B4: Case Guide
B5: 1 | C5: Base
B6: 2 | C6: Bull
B7: 3 | C7: Bear
B10: =CONCATENATE("Selected: ", CHOOSE($C$2,B20,B30,B41)) -> Selected: Base Case | C10: FY2016A | D10: 2017 | E10: =D10+1 -> 2018 | F10: =E10+1 -> 2019 | G10: =F10+1 -> 2020 | H10: =G10+1 -> 2021 | I10: =H10+1 -> 2022 | J10: =I10+1 -> 2023 | K10: =J10+1 -> 2024 | L10: =K10+1 -> 2025 | M10: =L10+1 -> 2026
B12: Revenue Growth | C12: =CHOOSE($C$2,C22,C32,C43) -> 0 | D12: =CHOOSE($C$2,D22,D32,D43) -> -0.03124249 | E12: =CHOOSE($C$2,E22,E32,E43) -> 0.3216737 | F12: =CHOOSE($C$2,F22,F32,F43) -> 0.081774385 | G12: =CHOOSE($C$2,G22,G32,G43) -> -0.010005784 | H12: =CHOOSE($C$2,H22,H32,H43) -> 0.18291757 | I12: =CHOOSE($C$2,I22,I32,I43) -> -0.017210736 | J12: =CHOOSE($C$2,J22,J32,J43) -> 0.031744318 | ... M12: =CHOOSE($C$2,M22,M32,M43) -> 0.032164629
B13: COGS as a % of Revenue | C13: =CHOOSE($C$2,C23,C33,C44) -> 0.4359529 | D13: =CHOOSE($C$2,D23,D33,D44) -> 0.43099314 | E13: =CHOOSE($C$2,E23,E33,E44) -> 0.42914346 | F13: =CHOOSE($C$2,F23,F33,F44) -> 0.39745518 | G13: =CHOOSE($C$2,G23,G33,G44) -> 0.43874511 | H13: =CHOOSE($C$2,H23,H33,H44) -> 0.42661004 | I13: =CHOOSE($C$2,I23,I33,I44) -> 0.4564833 | J13: =CHOOSE($C$2,J23,J33,J44) -> 0.4564833 | ... M13: =CHOOSE($C$2,M23,M33,M44) -> 0.4564833 | N13: Assumption 2
B14: OpEx as a % of Revenue | C14: =CHOOSE($C$2,C24,C34,C45) -> 0.3070576 | D14: =CHOOSE($C$2,D24,D34,D45) -> 0.30587943 | E14: =CHOOSE($C$2,E24,E34,E45) -> 0.31408371 | F14: =CHOOSE($C$2,F24,F34,F45) -> 0.31197224 | G14: =CHOOSE($C$2,G24,G34,G45) -> 0.31670269 | H14: =CHOOSE($C$2,H24,H34,H45) -> 0.30649941 | I14: =CHOOSE($C$2,I24,I34,I45) -> 0.35036585 | J14: =CHOOSE($C$2,J24,J34,J45) -> 0.35036585 | ... M14: =CHOOSE($C$2,M24,M34,M45) -> 0.35036585 | N14: Assumption 3
B15: D&A as a % of Revenue | C15: =CHOOSE($C$2,C25,C35,C46) -> 0.084114396 | D15: =CHOOSE($C$2,D25,D35,D46) -> 0.077648226 | E15: =CHOOSE($C$2,E25,E35,E46) -> 0.11606081 | F15: =CHOOSE($C$2,F25,F35,F46) -> 0.1231926 | G15: =CHOOSE($C$2,G25,G35,G46) -> 0.11859555 | H15: =CHOOSE($C$2,H25,H35,H46) -> 0.10539313 | I15: =CHOOSE($C$2,I25,I35,I46) -> 0.10416745 | J15: =CHOOSE($C$2,J25,J35,J46) -> 0.10416745 | ... M15: =CHOOSE($C$2,M25,M35,M46) -> 0.10416745 | N15: Assumption 4
B16: CAPEX as a % of Revenue | C16: =CHOOSE($C$2,C26,C36,C47) -> 0.057518225 | D16: =CHOOSE($C$2,D26,D36,D47) -> 0.060117423 | E16: =CHOOSE($C$2,E26,E36,E47) -> 0.055996997 | F16: =CHOOSE($C$2,F26,F36,F47) -> 0.055349913 | G16: =CHOOSE($C$2,G26,G36,G47) -> 0.047321376 | H16: =CHOOSE($C$2,H26,H36,H47) -> 0.060796128 | I16: =CHOOSE($C$2,I26,I36,I47) -> 0.066183344 | J16: =CHOOSE($C$2,J26,J36,J47) -> 0.076183344 | ... M16: =CHOOSE($C$2,M26,M36,M47) -> 0.10618334 | N16: Assumption 8
B17: Change in NWC as % of Revenue | C17: =CHOOSE($C$2,C27,C37,C48) -> 0.03196347 | D17: =CHOOSE($C$2,D27,D37,D48) -> -0.030678905 | E17: =CHOOSE($C$2,E27,E37,E48) -> 0.05612213 | F17: =CHOOSE($C$2,F27,F37,F48) -> -0.021341816 | G17: =CHOOSE($C$2,G27,G37,G48) -> 0.0066016241 | H17: =CHOOSE($C$2,H27,H37,H48) -> 0.016495456 | I17: =CHOOSE($C$2,I27,I37,I48) -> 0.0098603266 | J17: =CHOOSE($C$2,J27,J37,J48) -> 0.0098603266 | ... M17: =CHOOSE($C$2,M27,M37,M48) -> 0.0098603266 | N17: Assumption 7
B18: Effective Tax Rate | C18: =CHOOSE($C$2,C28,C38,C49) -> 0.091247672 | D18: =CHOOSE($C$2,D28,D38,D49) -> -0.12704918 | E18: =CHOOSE($C$2,E28,E38,E49) -> 0.73486786 | F18: =CHOOSE($C$2,F28,F38,F49) -> -0.048469388 | G18: =CHOOSE($C$2,G28,G38,G49) -> 0.11269036 | H18: =CHOOSE($C$2,H28,H38,H49) -> 0.06690455 | I18: =CHOOSE($C$2,I28,I38,I49) -> 0.21 | J18: =CHOOSE($C$2,J28,J38,J49) -> 0.21 | ... M18: =CHOOSE($C$2,M28,M38,M49) -> 0.21 | N18: Assumption 6
B20: Base Case | C20: FY2016A | D20: 2017 | E20: =D20+1 -> 2018 | F20: =E20+1 -> 2019 | G20: =F20+1 -> 2020 | H20: =G20+1 -> 2021 | I20: =H20+1 -> 2022 | J20: =I20+1 -> 2023 | K20: =J20+1 -> 2024 | L20: =K20+1 -> 2025 | M20: =L20+1 -> 2026
B22: Revenue Growth | D22: ='Revenue Model'!D14 -> -0.03124249 | E22: ='Revenue Model'!E14 -> 0.3216737 | F22: ='Revenue Model'!F14 -> 0.081774385 | G22: ='Revenue Model'!G14 -> -0.010005784 | H22: ='Revenue Model'!H14 -> 0.18291757 | I22: ='Revenue Model'!I14 -> -0.017210736 | J22: ='Revenue Model'!J14 -> 0.031744318 | K22: ='Revenue Model'!K14 -> 0.031884958 | ... M22: ='Revenue Model'!M14 -> 0.032164629 | N22: *See tab "Revenue Model" for assumptions
B23: COGS as a % of Revenue | C23: ='Historical Analysis'!C8 -> 0.4359529 | D23: ='Historical Analysis'!D8 -> 0.43099314 | E23: ='Historical Analysis'!E8 -> 0.42914346 | F23: ='Historical Analysis'!F8 -> 0.39745518 | G23: ='Historical Analysis'!G8 -> 0.43874511 | H23: ='Historical Analysis'!H8 -> 0.42661004 | I23: ='Historical Analysis'!$J$8+0.03 -> 0.4564833 | J23: ='Historical Analysis'!$J$8+0.03 -> 0.4564833 | K23: ='Historical Analysis'!$J$8+0.03 -> 0.4564833 | L23: ='Historical Analysis'!$J$8+0.03 -> 0.4564833 | M23: ='Historical Analysis'!$J$8+0.03 -> 0.4564833 | N23: *See tab "Historical Analysis" for assumptions
B24: OpEx as a % of Revenue | C24: ='Historical Analysis'!C11 -> 0.3070576 | D24: ='Historical Analysis'!D11 -> 0.30587943 | E24: ='Historical Analysis'!E11 -> 0.31408371 | F24: ='Historical Analysis'!F11 -> 0.31197224 | G24: ='Historical Analysis'!G11 -> 0.31670269 | H24: ='Historical Analysis'!H11 -> 0.30649941 | I24: ='Historical Analysis'!$J$11+0.04 -> 0.35036585 | J24: ='Historical Analysis'!$J$11+0.04 -> 0.35036585 | K24: ='Historical Analysis'!$J$11+0.04 -> 0.35036585 | L24: ='Historical Analysis'!$J$11+0.04 -> 0.35036585 | M24: ='Historical Analysis'!$J$11+0.04 -> 0.35036585 | N24: *See tab "Historical Analysis" for assumptions
B25: D&A as a % of Revenue | C25: ='Historical Analysis'!C14 -> 0.084114396 | D25: ='Historical Analysis'!D14 -> 0.077648226 | E25: ='Historical Analysis'!E14 -> 0.11606081 | F25: ='Historical Analysis'!F14 -> 0.1231926 | G25: ='Historical Analysis'!G14 -> 0.11859555 | H25: ='Historical Analysis'!H14 -> 0.10539313 | I25: ='Historical Analysis'!$J$14 -> 0.10416745 | J25: ='Historical Analysis'!$J$14 -> 0.10416745 | K25: ='Historical Analysis'!$J$14 -> 0.10416745 | L25: ='Historical Analysis'!$J$14 -> 0.10416745 | M25: ='Historical Analysis'!$J$14 -> 0.10416745 | N25: *See tab "Historical Analysis" for assumptions
B26: CAPEX as a % of Revenue | C26: ='Historical Analysis'!C29 -> 0.057518225 | D26: ='Historical Analysis'!D29 -> 0.060117423 | E26: ='Historical Analysis'!E29 -> 0.055996997 | F26: ='Historical Analysis'!F29 -> 0.055349913 | G26: ='Historical Analysis'!G29 -> 0.047321376 | H26: ='Historical Analysis'!H29 -> 0.060796128 | I26: ='Historical Analysis'!$J$29+0.01 -> 0.066183344 | J26: ='Historical Analysis'!$J$29+0.02 -> 0.076183344 | K26: ='Historical Analysis'!$J$29+0.03 -> 0.086183344 | L26: ='Historical Analysis'!$J$29+0.04 -> 0.096183344 | M26: ='Historical Analysis'!$J$29+0.05 -> 0.10618334 | N26: *See tab "Historical Analysis" for assumptions
B27: Change in NWC as % of Revenue | C27: ='Historical Analysis'!C26 -> 0.03196347 | D27: ='Historical Analysis'!D26 -> -0.030678905 | E27: ='Historical Analysis'!E26 -> 0.05612213 | F27: ='Historical Analysis'!F26 -> -0.021341816 | G27: ='Historical Analysis'!G26 -> 0.0066016241 | H27: ='Historical Analysis'!H26 -> 0.016495456 | I27: ='Historical Analysis'!$J$26 -> 0.0098603266 | J27: ='Historical Analysis'!$J$26 -> 0.0098603266 | K27: ='Historical Analysis'!$J$26 -> 0.0098603266 | L27: ='Historical Analysis'!$J$26 -> 0.0098603266 | M27: ='Historical Analysis'!$J$26 -> 0.0098603266 | N27: *See tab "Historical Analysis" for assumptions
B28: Effective Tax Rate | C28: ='Historical Analysis'!C17 -> 0.091247672 | D28: ='Historical Analysis'!D17 -> -0.12704918 | E28: ='Historical Analysis'!E17 -> 0.73486786 | F28: ='Historical Analysis'!F17 -> -0.048469388 | G28: ='Historical Analysis'!G17 -> 0.11269036 | H28: ='Historical Analysis'!H17 -> 0.06690455 | I28: 0.21 | J28: 0.21 | K28: 0.21 | L28: 0.21 | M28: 0.21 | N28: *See tab "Historical Analysis" for assumptions
B30: Bull Case | C30: FY2016A | D30: 2017 | E30: =D30+1 -> 2018 | F30: =E30+1 -> 2019 | G30: =F30+1 -> 2020 | H30: =G30+1 -> 2021 | I30: =H30+1 -> 2022 | J30: =I30+1 -> 2023 | K30: =J30+1 -> 2024 | L30: =K30+1 -> 2025 | M30: =L30+1 -> 2026
B32: Revenue Growth | D32: ='Revenue Model'!D29 -> -0.03124249 | E32: ='Revenue Model'!E29 -> 0.3216737 | F32: ='Revenue Model'!F29 -> 0.081774385 | G32: ='Revenue Model'!G29 -> -0.010005784 | H32: ='Revenue Model'!H29 -> 0.18291757 | I32: =I22+0.0025 -> -0.014710736 | J32: =J22+0.0025 -> 0.034244318 | K32: =K22+0.0025 -> 0.034384958 | L32: =L22+0.0025 -> 0.034525074 | M32: =M22+0.0025 -> 0.034664629 | N32: Assumption 9
B33: COGS as a % of Revenue | C33: ='Historical Analysis'!C8 -> 0.4359529 | D33: ='Historical Analysis'!D8 -> 0.43099314 | E33: ='Historical Analysis'!E8 -> 0.42914346 | F33: ='Historical Analysis'!F8 -> 0.39745518 | G33: ='Historical Analysis'!G8 -> 0.43874511 | H33: ='Historical Analysis'!H8 -> 0.42661004 | I33: =I23-0.01 -> 0.4464833 | J33: =J23-0.01 -> 0.4464833 | K33: =K23-0.01 -> 0.4464833 | L33: =L23-0.01 -> 0.4464833 | M33: =M23-0.01 -> 0.4464833 | N33: Assumption 10
B34: OpEx as a % of Revenue | C34: ='Historical Analysis'!C11 -> 0.3070576 | D34: ='Historical Analysis'!D11 -> 0.30587943 | E34: ='Historical Analysis'!E11 -> 0.31408371 | F34: ='Historical Analysis'!F11 -> 0.31197224 | G34: ='Historical Analysis'!G11 -> 0.31670269 | H34: ='Historical Analysis'!H11 -> 0.30649941 | I34: =I24-0.01 -> 0.34036585 | J34: =J24-0.01 -> 0.34036585 | K34: =K24-0.01 -> 0.34036585 | L34: =L24-0.01 -> 0.34036585 | M34: =M24-0.01 -> 0.34036585 | N34: Assumption 11
B35: D&A as a % of Revenue | C35: ='Historical Analysis'!C14 -> 0.084114396 | D35: ='Historical Analysis'!D14 -> 0.077648226 | E35: ='Historical Analysis'!E14 -> 0.11606081 | F35: ='Historical Analysis'!F14 -> 0.1231926 | G35: ='Historical Analysis'!G14 -> 0.11859555 | H35: ='Historical Analysis'!H14 -> 0.10539313 | I35: =I25-0.01 -> 0.094167451 | J35: =J25-0.01 -> 0.094167451 | K35: =K25-0.01 -> 0.094167451 | L35: =L25-0.01 -> 0.094167451 | M35: =M25-0.01 -> 0.094167451 | N35: Assumption 12
B36: CAPEX as a % of Revenue | C36: ='Historical Analysis'!C29 -> 0.057518225 | D36: ='Historical Analysis'!D29 -> 0.060117423 | E36: ='Historical Analysis'!E29 -> 0.055996997 | F36: ='Historical Analysis'!F29 -> 0.055349913 | G36: ='Historical Analysis'!G29 -> 0.047321376 | H36: ='Historical Analysis'!H29 -> 0.060796128 | I36: =I26-0.002 -> 0.064183344 | J36: =J26-0.002 -> 0.074183344 | K36: =K26-0.002 -> 0.084183344 | L36: =L26-0.002 -> 0.094183344 | M36: =M26-0.002 -> 0.10418334 | N36: Assumption 13
B37: Change in NWC as % of Revenue | C37: ='Historical Analysis'!C26 -> 0.03196347 | D37: ='Historical Analysis'!D26 -> -0.030678905 | E37: ='Historical Analysis'!E26 -> 0.05612213 | F37: ='Historical Analysis'!F26 -> -0.021341816 | G37: ='Historical Analysis'!G26 -> 0.0066016241 | H37: ='Historical Analysis'!H26 -> 0.016495456 | I37: =I27+0.005 -> 0.014860327 | J37: =J27+0.005 -> 0.014860327 | K37: =K27+0.005 -> 0.014860327 | L37: =L27+0.005 -> 0.014860327 | M37: =M27+0.005 -> 0.014860327 | N37: Assumption 14
B38: Effective Tax Rate | C38: ='Historical Analysis'!C17 -> 0.091247672 | D38: ='Historical Analysis'!D17 -> -0.12704918 | E38: ='Historical Analysis'!E17 -> 0.73486786 | F38: ='Historical Analysis'!F17 -> -0.048469388 | G38: ='Historical Analysis'!G17 -> 0.11269036 | H38: ='Historical Analysis'!H17 -> 0.06690455 | I38: =I28-0.02 -> 0.19 | J38: =J28-0.02 -> 0.19 | K38: =K28-0.02 -> 0.19 | L38: =L28-0.02 -> 0.19 | M38: =M28-0.02 -> 0.19 | N38: Assumption 15
B41: Bear Case | C41: FY2016A | D41: 2017 | E41: =D41+1 -> 2018 | F41: =E41+1 -> 2019 | G41: =F41+1 -> 2020 | H41: =G41+1 -> 2021 | I41: =H41+1 -> 2022 | J41: =I41+1 -> 2023 | K41: =J41+1 -> 2024 | L41: =K41+1 -> 2025 | M41: =L41+1 -> 2026
B43: Revenue Growth | D43: ='Revenue Model'!D29 -> -0.03124249 | E43: ='Revenue Model'!E29 -> 0.3216737 | F43: ='Revenue Model'!F29 -> 0.081774385 | G43: ='Revenue Model'!G29 -> -0.010005784 | H43: ='Revenue Model'!H29 -> 0.18291757 | I43: =I22-0.0025 -> -0.019710736 | J43: =J22-0.0025 -> 0.029244318 | K43: =K22-0.0025 -> 0.029384958 | L43: =L22-0.0025 -> 0.029525074 | M43: =M22-0.0025 -> 0.029664629 | N43: Assumption 16
B44: COGS as a % of Revenue | C44: ='Historical Analysis'!C8 -> 0.4359529 | D44: ='Historical Analysis'!D8 -> 0.43099314 | E44: ='Historical Analysis'!E8 -> 0.42914346 | F44: ='Historical Analysis'!F8 -> 0.39745518 | G44: ='Historical Analysis'!G8 -> 0.43874511 | H44: ='Historical Analysis'!H8 -> 0.42661004 | I44: =I23+0.03 -> 0.4864833 | J44: =J23+0.03 -> 0.4864833 | K44: =K23+0.03 -> 0.4864833 | L44: =L23+0.03 -> 0.4864833 | M44: =M23+0.03 -> 0.4864833 | N44: Assumption 17
B45: OpEx as a % of Revenue | C45: ='Historical Analysis'!C11 -> 0.3070576 | D45: ='Historical Analysis'!D11 -> 0.30587943 | E45: ='Historical Analysis'!E11 -> 0.31408371 | F45: ='Historical Analysis'!F11 -> 0.31197224 | G45: ='Historical Analysis'!G11 -> 0.31670269 | H45: ='Historical Analysis'!H11 -> 0.30649941 | I45: =I24+0.02 -> 0.37036585 | J45: =J24+0.02 -> 0.37036585 | K45: =K24+0.02 -> 0.37036585 | L45: =L24+0.02 -> 0.37036585 | M45: =M24+0.02 -> 0.37036585 | N45: Assumption 18
B46: D&A as a % of Revenue | C46: ='Historical Analysis'!C14 -> 0.084114396 | D46: ='Historical Analysis'!D14 -> 0.077648226 | E46: ='Historical Analysis'!E14 -> 0.11606081 | F46: ='Historical Analysis'!F14 -> 0.1231926 | G46: ='Historical Analysis'!G14 -> 0.11859555 | H46: ='Historical Analysis'!H14 -> 0.10539313 | I46: =I25+0.01 -> 0.11416745 | J46: =J25+0.01 -> 0.11416745 | K46: =K25+0.01 -> 0.11416745 | L46: =L25+0.01 -> 0.11416745 | M46: =M25+0.01 -> 0.11416745 | N46: Assumption 19
B47: CAPEX as a % of Revenue | C47: ='Historical Analysis'!C29 -> 0.057518225 | D47: ='Historical Analysis'!D29 -> 0.060117423 | E47: ='Historical Analysis'!E29 -> 0.055996997 | F47: ='Historical Analysis'!F29 -> 0.055349913 | G47: ='Historical Analysis'!G29 -> 0.047321376 | H47: ='Historical Analysis'!H29 -> 0.060796128 | I47: =I26+0.02 -> 0.086183344 | J47: =J26+0.02 -> 0.096183344 | K47: =K26+0.02 -> 0.10618334 | L47: =L26+0.02 -> 0.11618334 | M47: =M26+0.02 -> 0.12618334 | N47: Assumption 20
B48: Change in NWC as % of Revenue | C48: ='Historical Analysis'!C26 -> 0.03196347 | D48: ='Historical Analysis'!D26 -> -0.030678905 | E48: ='Historical Analysis'!E26 -> 0.05612213 | F48: ='Historical Analysis'!F26 -> -0.021341816 | G48: ='Historical Analysis'!G26 -> 0.0066016241 | H48: ='Historical Analysis'!H26 -> 0.016495456 | I48: =I27-0.005 -> 0.0048603266 | J48: =J27-0.005 -> 0.0048603266 | K48: =K27-0.005 -> 0.0048603266 | L48: =L27-0.005 -> 0.0048603266 | M48: =M27-0.005 -> 0.0048603266 | N48: Assumption 21
B49: Effective Tax Rate | C49: ='Historical Analysis'!C17 -> 0.091247672 | D49: ='Historical Analysis'!D17 -> -0.12704918 | E49: ='Historical Analysis'!E17 -> 0.73486786 | F49: ='Historical Analysis'!F17 -> -0.048469388 | G49: ='Historical Analysis'!G17 -> 0.11269036 | H49: ='Historical Analysis'!H17 -> 0.06690455 | I49: =I28+0.01 -> 0.22 | J49: =J28+0.01 -> 0.22 | K49: =K28+0.01 -> 0.22 | L49: =L28+0.01 -> 0.22 | M49: =M28+0.01 -> 0.22 | N49: Assumption 22

Sheet Historical Analysis
B2: Analysis | C2: FY2016A | D2: 2017 | E2: =D2+1 -> 2018 | F2: =E2+1 -> 2019 | G2: =F2+1 -> 2020 | H2: =G2+1 -> 2021 | J2: Average | K2: Standard Deviation | L2: Correl. with Revenue
B3: (millions of dollars)
B4: From Income Statement
B5: Revenue | C5: ='Income Statement'!B11 -> 12483 | D5: ='Income Statement'!C11 -> 12093 | E5: ='Income Statement'!D11 -> 15983 | F5: ='Income Statement'!E11 -> 17290 | G5: ='Income Statement'!F11 -> 17117 | H5: ='Income Statement'!G11 -> 20248 | L5: =CORREL(C5:H5,C5:H5) -> 1
B6: Revenue Annual Growth Rate | D6: =D5/C5-1 -> -0.03124249 | E6: =E5/D5-1 -> 0.3216737 | F6: =F5/E5-1 -> 0.081774385 | G6: =G5/F5-1 -> -0.010005784 | H6: =H5/G5-1 -> 0.18291757 | J6: =AVERAGE(C6:H6) -> 0.10902347 | K6: =_xlfn.STDEV.S(C6:H6) -> 0.14600126 | L6: =CORREL(D6:H6,D6:H6) -> 1
B7: COGS | C7: ='Income Statement'!B13 -> 5442 | D7: ='Income Statement'!C13 -> 5212 | E7: ='Income Statement'!D13 -> 6859 | F7: ='Income Statement'!E13 -> 6872 | G7: ='Income Statement'!F13 -> 7510 | H7: ='Income Statement'!G13 -> 8638
B8: COGS as a % of Revenue | C8: =C7/C5 -> 0.4359529 | D8: =D7/D5 -> 0.43099314 | E8: =E7/E5 -> 0.42914346 | F8: =F7/F5 -> 0.39745518 | G8: =G7/G5 -> 0.43874511 | H8: =H7/H5 -> 0.42661004 | J8: =AVERAGE(C8:H8) -> 0.4264833 | K8: =_xlfn.STDEV.S(C8:H8) -> 0.014900257 | L8: =CORREL(C5:H5,C7:H7) -> 0.98216784
B9: COGS Annual Growth Rate | D9: =D7/C7-1 -> -0.042263874 | E9: =E7/D7-1 -> 0.31600153 | F9: =F7/E7-1 -> 0.00189532 | G9: =G7/F7-1 -> 0.092840512 | H9: =H7/G7-1 -> 0.15019973 | J9: =AVERAGE(C9:H9) -> 0.10373465 | K9: =_xlfn.STDEV.S(C9:H9) -> 0.14055402 | L9: =CORREL(D6:H6,D9:H9) -> 0.89082207
B10: OpEx | C10: ='Income Statement'!B18 -> 3833 | D10: ='Income Statement'!C18 -> 3699 | E10: ='Income Statement'!D18 -> 5020 | F10: ='Income Statement'!E18 -> 5394 | G10: ='Income Statement'!F18 -> 5421 | H10: ='Income Statement'!G18 -> 6206
B11: OpEx as a % of Revenue | C11: =C10/C5 -> 0.3070576 | D11: =D10/D5 -> 0.30587943 | E11: =E10/E5 -> 0.31408371 | F11: =F10/F5 -> 0.31197224 | G11: =G10/G5 -> 0.31670269 | H11: =H10/H5 -> 0.30649941 | J11: =AVERAGE(C11:H11) -> 0.31036585 | K11: =_xlfn.STDEV.S(C11:H11) -> 0.0045294682 | L11: =CORREL(C5:H5,C10:H10) -> 0.99728694
B12: OpEx Annual Growth Rate | D12: =D11/C11-1 -> -0.0038369477 | E12: =E11/D11-1 -> 0.026821939 | F12: =F11/E11-1 -> -0.0067226525 | G12: =G11/F11-1 -> 0.015163064 | H12: =H11/G11-1 -> -0.032217237 | J12: =AVERAGE(C12:H12) -> -0.00015836696 | K12: =_xlfn.STDEV.S(C12:H12) -> 0.022622313 | L12: =CORREL(D12:H12,D6:H6) -> 0.16951529
B13: D&A | C13: ='Income Statement'!B14 -> 1050 | D13: ='Income Statement'!C14 -> 939 | E13: ='Income Statement'!D14 -> 1855 | F13: ='Income Statement'!E14 -> 2130 | G13: ='Income Statement'!F14 -> 2030 | H13: ='Income Statement'!G14 -> 2134
B14: D&A as a % of Revenue | C14: =C13/C5 -> 0.084114396 | D14: =D13/D5 -> 0.077648226 | E14: =E13/E5 -> 0.11606081 | F14: =F13/F5 -> 0.1231926 | G14: =G13/G5 -> 0.11859555 | H14: =H13/H5 -> 0.10539313 | J14: =AVERAGE(C14:H14) -> 0.10416745 | K14: =_xlfn.STDEV.S(C14:H14) -> 0.019070788 | L14: =CORREL(C5:H5,C13:H13) -> 0.93762477
B15: D&A as a % of Net PPE | C15: =C13/C20 -> 0.26916175 | D15: =D13/D20 -> 0.20245796 | E15: =E13/E20 -> 0.34511628 | F15: =F13/F20 -> 0.37639159 | G15: =G13/G20 -> 0.32013878 | H15: =H13/H20 -> 0.31203392 | J15: =AVERAGE(C15:H15) -> 0.30421671 | K15: =_xlfn.STDEV.S(C15:H15) -> 0.061286708 | L15: =CORREL(C20:H20,C13:H13) -> 0.87720662
B16: D&A Annual Growth Rate | D16: =D13/C13-1 -> -0.10571429 | E16: =E13/D13-1 -> 0.97550586 | F16: =F13/E13-1 -> 0.14824798 | G16: =G13/F13-1 -> -0.046948357 | H16: =H13/G13-1 -> 0.051231527 | J16: =AVERAGE(C16:H16) -> 0.20446454 | K16: =_xlfn.STDEV.S(C16:H16) -> 0.44174787 | L16: =CORREL(D16:H16,D6:H6) -> 0.88224411
B17: Effective Tax Rate | C17: ='Income Statement'!B42/'Income Statement'!B41 -> 0.091247672 | D17: ='Income Statement'!C42/'Income Statement'!C41 -> -0.12704918 | E17: ='Income Statement'!D42/'Income Statement'!D41 -> 0.73486786 | F17: ='Income Statement'!E42/'Income Statement'!E41 -> -0.048469388 | G17: ='Income Statement'!F42/'Income Statement'!F41 -> 0.11269036 | H17: ='Income Statement'!G42/'Income Statement'!G41 -> 0.06690455 | J17: =AVERAGE(C17:H17) -> 0.13836531 | K17: =_xlfn.STDEV.S(C17:H17) -> 0.30631789 | L17: =CORREL(C5:H5,C17:H17) -> 0.12984164
B19: From Balance Sheet
B20: Net PPE | C20: ='Balance Sheet'!B26 -> 3901 | D20: ='Balance Sheet'!C26 -> 4638 | E20: ='Balance Sheet'!D26 -> 5375 | F20: ='Balance Sheet'!E26 -> 5659 | G20: ='Balance Sheet'!F26 -> 6341 | H20: ='Balance Sheet'!G26 -> 6839
B21: Net PPE as a % of Revenue | C21: =C20/C5 -> 0.31250501 | D21: =D20/D5 -> 0.38352766 | E21: =E20/E5 -> 0.33629481 | F21: =F20/F5 -> 0.32729902 | G21: =G20/G5 -> 0.37045043 | H21: =H20/H5 -> 0.33776175 | J21: =AVERAGE(C21:H21) -> 0.34463978 | K21: =_xlfn.STDEV.S(C21:H21) -> 0.026939741 | L21: =CORREL(C5:H5,C20:H20) -> 0.93930205
B22: Net PPE Annual Growth Rate | D22: =D20/C20-1 -> 0.18892592 | E22: =E20/D20-1 -> 0.1589047 | F22: =F20/E20-1 -> 0.052837209 | G22: =G20/F20-1 -> 0.12051599 | H22: =H20/G20-1 -> 0.078536508 | J22: =AVERAGE(C22:H22) -> 0.11994407 | K22: =_xlfn.STDEV.S(C22:H22) -> 0.05588978 | L22: =CORREL(D22:H22,$D$6:$H$6) -> -0.082416501
B24: From Cash Flow Statement
B25: Change in NWC | C25: ='Cash Flow Statement'!B20 -> 399 | D25: ='Cash Flow Statement'!C20 -> -371 | E25: ='Cash Flow Statement'!D20 -> 897 | F25: ='Cash Flow Statement'!E20 -> -369 | G25: ='Cash Flow Statement'!F20 -> 113 | H25: ='Cash Flow Statement'!G20 -> 334
B26: Change in NWC as % of Revenue | C26: =C25/C5 -> 0.03196347 | D26: =D25/D5 -> -0.030678905 | E26: =E25/E5 -> 0.05612213 | F26: =F25/F5 -> -0.021341816 | G26: =G25/G5 -> 0.0066016241 | H26: =H25/H5 -> 0.016495456 | J26: =AVERAGE(C26:H26) -> 0.0098603266 | K26: =_xlfn.STDEV.S(C26:H26) -> 0.032558718 | L26: =CORREL(C5:H5,C25:H25) -> 0.16181875
B27: Change in NWC Annual Growth Rate | D27: =D25/C25-1 -> -1.9298246 | E27: =E25/D25-1 -> -3.4177898 | F27: =F25/E25-1 -> -1.4113712 | G27: =G25/F25-1 -> -1.3062331 | H27: =H25/G25-1 -> 1.9557522 | J27: =AVERAGE(C27:H27) -> -1.2218933 | K27: =_xlfn.STDEV.S(C27:H27) -> 1.9661876 | L27: =CORREL(D27:H27,$D$6:$H$6) -> -0.1024573
B28: CAPEX | C28: =-'Cash Flow Statement'!B26 -> 718 | D28: =-'Cash Flow Statement'!C26 -> 727 | E28: =-'Cash Flow Statement'!D26 -> 895 | F28: =-'Cash Flow Statement'!E26 -> 957 | G28: =-'Cash Flow Statement'!F26 -> 810 | H28: =-'Cash Flow Statement'!G26 -> 1231
B29: CAPEX as a % of Revenue | C29: =C28/C5 -> 0.057518225 | D29: =D28/D5 -> 0.060117423 | E29: =E28/E5 -> 0.055996997 | F29: =F28/F5 -> 0.055349913 | G29: =G28/G5 -> 0.047321376 | H29: =H28/H5 -> 0.060796128 | J29: =AVERAGE(C29:H29) -> 0.056183344 | K29: =_xlfn.STDEV.S(C29:H29) -> 0.004853874 | L29: =CORREL(C5:H5,C28:H28) -> 0.90119713
B30: CAPEX as a % of Net PPE | C30: =C28/C20 -> 0.18405537 | D30: =D28/D20 -> 0.1567486 | E30: =E28/E20 -> 0.16651163 | F30: =F28/F20 -> 0.16911115 | G30: =G28/G20 -> 0.1277401 | H30: =H28/H20 -> 0.17999708 | J30: =AVERAGE(C30:H30) -> 0.16402732 | K30: =_xlfn.STDEV.S(C30:H30) -> 0.020287508 | L30: =CORREL(C20:H20,C28:H28) -> 0.78804225
B31: CAPEX Annual Growth Rate | D31: =D28/C28-1 -> 0.012534819 | E31: =E28/D28-1 -> 0.23108666 | F31: =F28/E28-1 -> 0.069273743 | G31: =G28/F28-1 -> -0.15360502 | H31: =H28/G28-1 -> 0.51975309 | J31: =AVERAGE(C31:H31) -> 0.13580866 | K31: =_xlfn.STDEV.S(C31:H31) -> 0.2548896 | L31: =CORREL(C6:H6,C31:H31) -> 0.68646471

Sheet Revenue Model
B2: Revenue Build | C2: FY2016A | D2: 2017 | E2: =D2+1 -> 2018 | F2: =E2+1 -> 2019 | G2: =F2+1 -> 2020 | H2: =G2+1 -> 2021 | I2: =H2+1 -> 2022 | J2: =I2+1 -> 2023 | K2: =J2+1 -> 2024 | L2: =K2+1 -> 2025 | M2: =L2+1 -> 2026
B3: (millions of dollars)
B4: Medical | C4: ='Segments '!F6 -> 8654 | D4: ='Segments '!G6 -> 8105 | E4: ='Segments '!H6 -> 8616 | F4: ='Segments '!I6 -> 9064 | G4: ='Segments '!J6 -> 8680 | H4: ='Segments '!K6 -> 9479 | I4: =H4*(1+I5) -> 8487.5266 | J4: =I4*(1+J5) -> 8638.4259 | K4: =J4*(1+K5) -> 8792.0081 | L4: =K4*(1+L5) -> 8948.3207 | M4: =L4*(1+M5) -> 9107.4124
B5: Annual Growth Rate | D5: =D4/C4-1 -> -0.063438872 | E5: =E4/D4-1 -> 0.063047502 | F5: =F4/E4-1 -> 0.051996286 | G5: =G4/F4-1 -> -0.042365402 | H5: =H4/G4-1 -> 0.092050691 | I5: =((9479-1160)*(1+J20))/H4-1 -> -0.10459683 | J5: =$J$20*(9479-1160)/9479 -> 0.017778947 | K5: =$J$20*(9479-1160)/9479 -> 0.017778947 | L5: =$J$20*(9479-1160)/9479 -> 0.017778947 | M5: =$J$20*(9479-1160)/9479 -> 0.017778947 | N5: Assumption 23
B6: % of Total Revenues | D6: =D4/D13 -> 0.67022244 | E6: =E4/E13 -> 0.53907276 | F6: =F4/F13 -> 0.52423366 | G6: =G4/G13 -> 0.50709821 | H6: =H4/H13 -> 0.468145 | I6: =I4/I13 -> 0.42651923 | J6: =J4/J13 -> 0.420746 | K6: =K4/K13 -> 0.41499434 | ... M6: =M4/M13 -> 0.40356164
B7: Life Sciences | C7: ='Segments '!F7 -> 3829 | D7: ='Segments '!G7 -> 3988 | E7: ='Segments '!H7 -> 4330 | F7: ='Segments '!I7 -> 4300 | G7: ='Segments '!J7 -> 4675 | H7: ='Segments '!K7 -> 6530 | I7: =H7*(1+I8) -> 6992.7874 | J7: =I7*(1+J8) -> 7285.7211 | K7: =J7*(1+K8) -> 7590.9261 | L7: =K7*(1+L8) -> 7908.9164 | M7: =L7*(1+M8) -> 8240.2276
B8: Annual Growth Rate | D8: =D7/C7-1 -> 0.041525202 | E8: =E7/D7-1 -> 0.085757272 | F8: =F7/E7-1 -> -0.0069284065 | G8: =G7/F7-1 -> 0.087209302 | H8: =H7/G7-1 -> 0.39679144 | I8: =J23-0.05 -> 0.070870963 | J8: =AVERAGE($D$8:$G$8)-0.01 -> 0.041890843 | K8: =AVERAGE($D$8:$G$8)-0.01 -> 0.041890843 | L8: =AVERAGE($D$8:$G$8)-0.01 -> 0.041890843 | M8: =AVERAGE($D$8:$G$8)-0.01 -> 0.041890843 | N8: Assumption 24
B9: % of Total Revenues | D9: =D7/D13 -> 0.32977756 | E9: =E7/E13 -> 0.27091284 | F9: =F7/F13 -> 0.24869867 | G9: =G7/G13 -> 0.27312029 | H9: =H7/H13 -> 0.32250099 | I9: =I7/I13 -> 0.35140488 | J9: =J7/J13 -> 0.35486071 | K9: =K7/K13 -> 0.35830169 | ... M9: =M7/M13 -> 0.36513552
B10: Interventional | C10: 0 | D10: 0 | E10: ='Segments '!H8 -> 3037 | F10: ='Segments '!I8 -> 3926 | G10: ='Segments '!J8 -> 3762 | H10: ='Segments '!K8 -> 4239 | I10: =H10*(1+I11) -> 4419.203 | J10: =I10*(1+J11) -> 4607.0665 | K10: =J10*(1+K11) -> 4802.9163 | L10: =K10*(1+L11) -> 5007.0918 | M10: =L10*(1+M11) -> 5219.9469
B11: Annual Growth Rate | D11: n/a | E11: n/a | F11: =F10/E10-1 -> 0.29272308 | G11: =G10/F10-1 -> -0.041772797 | H11: =H10/G10-1 -> 0.12679426 | I11: =AVERAGE($G$11:$H$11) -> 0.042510731 | J11: =AVERAGE($G$11:$H$11) -> 0.042510731 | K11: =AVERAGE($G$11:$H$11) -> 0.042510731 | L11: =AVERAGE($G$11:$H$11) -> 0.042510731 | M11: =AVERAGE($G$11:$H$11) -> 0.042510731 | N11: Assumption 25
B12: % of Total Revenues | D12: n/a | E12: =E10/E13 -> 0.19001439 | F12: =F10/F13 -> 0.22706767 | G12: =G10/G13 -> 0.2197815 | H12: =H10/H13 -> 0.20935401 | I12: =I10/I13 -> 0.22207589 | J12: =J10/J13 -> 0.22439329 | K12: =K10/K13 -> 0.22670396 | L12: =L10/L13 -> 0.22900734 | M12: =M10/M13 -> 0.23130284
B13: Total Revenue | C13: =C4+C7+C10 -> 12483 | D13: =D4+D7+D10 -> 12093 | E13: =E4+E7+E10 -> 15983 | F13: =F4+F7+F10 -> 17290 | G13: =G4+G7+G10 -> 17117 | H13: =H4+H7+H10 -> 20248 | I13: =I4+I7+I10 -> 19899.517 | J13: =J4+J7+J10 -> 20531.214 | ... M13: =M4+M7+M10 -> 22567.587
B14: Annual Growth Rate | D14: =D13/C13-1 -> -0.03124249 | E14: =E13/D13-1 -> 0.3216737 | F14: =F13/E13-1 -> 0.081774385 | G14: =G13/F13-1 -> -0.010005784 | H14: =H13/G13-1 -> 0.18291757 | I14: =I13/H13-1 -> -0.017210736 | J14: =J13/I13-1 -> 0.031744318 | K14: =K13/J13-1 -> 0.031884958 | ... M14: =M13/L13-1 -> 0.032164629 | N14: Assumption 1
B17: Analysis | C17: FY2016A | D17: 2017 | E17: =D17+1 -> 2018 | F17: =E17+1 -> 2019 | G17: =F17+1 -> 2020 | H17: =G17+1 -> 2021 | J17: Average | K17: Standard Deviation
B18: (millions of dollars)
B19: Medical | C19: ='Segments '!$F$6 -> 8654 | D19: ='Segments '!$G$6 -> 8105 | E19: ='Segments '!$H$6 -> 8616 | F19: ='Segments '!$I$6 -> 9064 | G19: ='Segments '!$J$6 -> 8680 | H19: ='Segments '!$K$6 -> 9479
B20: Annual Growth Rate | D20: =D19/C19-1 -> -0.063438872 | E20: =E19/D19-1 -> 0.063047502 | F20: =F19/E19-1 -> 0.051996286 | G20: =G19/F19-1 -> -0.042365402 | H20: =H19/G19-1 -> 0.092050691 | J20: =AVERAGE(C20:H20) -> 0.020258041 | K20: =_xlfn.STDEV.S(C20:H20) -> 0.068773737
B21: % of Total Revenues | D21: =D19/D28 -> 0.67022244 | E21: =E19/E28 -> 0.53907276 | F21: =F19/F28 -> 0.52423366 | G21: =G19/G28 -> 0.50709821 | H21: =H19/H28 -> 0.468145
B22: Life Sciences | C22: ='Segments '!$F$7 -> 3829 | D22: ='Segments '!$G$7 -> 3988 | E22: ='Segments '!$H$7 -> 4330 | F22: ='Segments '!$I$7 -> 4300 | G22: ='Segments '!$J$7 -> 4675 | H22: ='Segments '!$K$7 -> 6530
B23: Annual Growth Rate | D23: =D22/C22-1 -> 0.041525202 | E23: =E22/D22-1 -> 0.085757272 | F23: =F22/E22-1 -> -0.0069284065 | G23: =G22/F22-1 -> 0.087209302 | H23: =H22/G22-1 -> 0.39679144 | J23: =AVERAGE(C23:H23) -> 0.12087096 | K23: =_xlfn.STDEV.S(C23:H23) -> 0.15900206
B24: % of Total Revenues | D24: =D22/D28 -> 0.32977756 | E24: =E22/E28 -> 0.27091284 | F24: =F22/F28 -> 0.24869867 | G24: =G22/G28 -> 0.27312029 | H24: =H22/H28 -> 0.32250099
B25: Interventional | C25: 0 | D25: 0 | E25: ='Segments '!$H$8 -> 3037 | F25: ='Segments '!$I$8 -> 3926 | G25: ='Segments '!$J$8 -> 3762 | H25: ='Segments '!$K$8 -> 4239
B26: Annual Growth Rate | F26: =F25/E25-1 -> 0.29272308 | G26: =G25/F25-1 -> -0.041772797 | H26: =H25/G25-1 -> 0.12679426 | J26: =AVERAGE(C26:H26) -> 0.12591485 | K26: =_xlfn.STDEV.S(C26:H26) -> 0.16724967
B27: % of Total Revenues | E27: =E25/E28 -> 0.19001439 | F27: =F25/F28 -> 0.22706767 | G27: =G25/G28 -> 0.2197815 | H27: =H25/H28 -> 0.20935401
C28: =C19+C22+C25 -> 12483 | D28: =D19+D22+D25 -> 12093 | E28: =E19+E22+E25 -> 15983 | F28: =F19+F22+F25 -> 17290 | G28: =G19+G22+G25 -> 17117 | H28: =H19+H22+H25 -> 20248
B29: Annual Growth Rate | D29: =D28/C28-1 -> -0.03124249 | E29: =E28/D28-1 -> 0.3216737 | F29: =F28/E28-1 -> 0.081774385 | G29: =G28/F28-1 -> -0.010005784 | H29: =H28/G28-1 -> 0.18291757 | J29: =AVERAGE(C29:H29) -> 0.10902347 | K29: =_xlfn.STDEV.S(C29:H29) -> 0.14600126

Sheet DCF Valuation
B2: Scenarios & Other Inputs
B3: Case Number | C3: 1
B4: Selected Case | C4: {=_xlfn.IFS(C3=1, "Base", C3=2, "Bull", C3=3, "Bear")} -> Base
B5: Risk Free Rate | C5: 0.0247 | D5: Assumption 29
B6: Beta | C6: ='Cost of Equity'!X19 -> 0.66554845
B7: Cost of Equity | C7: =WACC!B7 -> 0.061305165
B8: Cost of Debt | C8: =WACC!B5 -> 0.024109514
B9: Terminal Growth Rate | C9: 0.02
B10: Tax Rate | C10: 0.21
B11: WACC | C11: =WACC!E7 -> 0.052902418
B13: Case Guide
B14: 1 | C14: Base
B15: 2 | C15: Bull
B16: 3 | C16: Bear
B18: DCF Projections
B19: FY Ending September | J19: 1 | K19: 2 | L19: 3 | M19: 4 | N19: 5
B20: FCF | D20: FY2016A | E20: 2017 | F20: =E20+1 -> 2018 | G20: =F20+1 -> 2019 | H20: =G20+1 -> 2020 | I20: =H20+1 -> 2021 | J20: =I20+1 -> 2022 | K20: =J20+1 -> 2023 | L20: =K20+1 -> 2024 | M20: =L20+1 -> 2025 | N20: =M20+1 -> 2026
B21: (millions of dollars)
B22: Revenue | D22: ='Revenue Model'!C13 -> 12483 | E22: ='Revenue Model'!D13 -> 12093 | F22: ='Revenue Model'!E13 -> 15983 | G22: ='Revenue Model'!F13 -> 17290 | H22: ='Revenue Model'!G13 -> 17117 | I22: =H22*(1+Inputs!H12) -> 20248 | J22: =I22*(1+Inputs!I12) -> 19899.517 | K22: =J22*(1+Inputs!J12) -> 20531.214 | L22: =K22*(1+Inputs!K12) -> 21185.85 | M22: =L22*(1+Inputs!L12) -> 21864.329 | N22: =M22*(1+Inputs!M12) -> 22567.587
B23: COGS | D23: ='DCF Valuation'!D22*Inputs!C23 -> 5442 | E23: ='DCF Valuation'!E22*Inputs!D23 -> 5212 | F23: ='DCF Valuation'!F22*Inputs!E23 -> 6859 | G23: ='DCF Valuation'!G22*Inputs!F23 -> 6872 | H23: ='DCF Valuation'!H22*Inputs!G23 -> 7510 | I23: ='DCF Valuation'!I22*Inputs!H23 -> 8638 | J23: ='DCF Valuation'!J22*Inputs!I23 -> 9083.7973 | K23: ='DCF Valuation'!K22*Inputs!J23 -> 9372.1562 | ... N23: ='DCF Valuation'!N22*Inputs!M23 -> 10301.727
B24: OpEx | D24: =D22*Inputs!C24 -> 3833 | E24: =E22*Inputs!D24 -> 3699 | F24: =F22*Inputs!E24 -> 5020 | G24: =G22*Inputs!F24 -> 5394 | H24: =H22*Inputs!G24 -> 5421 | I24: =I22*Inputs!H24 -> 6206 | J24: =J22*Inputs!I24 -> 6972.1111 | K24: =K22*Inputs!J24 -> 7193.4361 | ... N24: =N22*Inputs!M24 -> 7906.9117
B25: EBIT | D25: =D22-D23-D24 -> 3208 | E25: =E22-E23-E24 -> 3182 | F25: =F22-F23-F24 -> 4104 | G25: =G22-G23-G24 -> 5024 | H25: =H22-H23-H24 -> 4186 | I25: =I22-I23-I24 -> 5404 | J25: =J22-J23-J24 -> 3843.6086 | K25: =K22-K23-K24 -> 3965.6214 | ... N25: =N22-N23-N24 -> 4358.9486
B26: Taxes | D26: =D25*Inputs!C28 -> 292.72253 | E26: =E25*Inputs!D28 -> -404.27049 | F26: =F25*Inputs!E28 -> 3015.8977 | G26: =G25*Inputs!F28 -> -243.5102 | H26: =H25*Inputs!G28 -> 471.72183 | I26: =I25*Inputs!H28 -> 361.55219 | J26: =J25*Inputs!I28 -> 807.15781 | K26: =K25*Inputs!J28 -> 832.78048 | ... N26: =N25*Inputs!M28 -> 915.3792
B27: NOPAT | D27: =D25-D26 -> 2915.2775 | E27: =E25-E26 -> 3586.2705 | F27: =F25-F26 -> 1088.1023 | G27: =G25-G26 -> 5267.5102 | H27: =H25-H26 -> 3714.2782 | I27: =I25-I26 -> 5042.4478 | J27: =J25-J26 -> 3036.4508 | K27: =K25-K26 -> 3132.8409 | ... N27: =N25-N26 -> 3443.5694
B28: + D&A | D28: ='DCF Valuation'!D22*Inputs!C25 -> 1050 | E28: ='DCF Valuation'!E22*Inputs!D25 -> 939 | F28: ='DCF Valuation'!F22*Inputs!E25 -> 1855 | G28: ='DCF Valuation'!G22*Inputs!F25 -> 2130 | H28: ='DCF Valuation'!H22*Inputs!G25 -> 2030 | I28: ='DCF Valuation'!I22*Inputs!H25 -> 2134 | J28: ='DCF Valuation'!J22*Inputs!I25 -> 2072.882 | K28: ='DCF Valuation'!K22*Inputs!J25 -> 2138.6842 | ... N28: ='DCF Valuation'!N22*Inputs!M25 -> 2350.808
B29: - Change in NWC | D29: =D22*Inputs!C27 -> 399 | E29: =E22*Inputs!D27 -> -371 | F29: =F22*Inputs!E27 -> 897 | G29: =G22*Inputs!F27 -> -369 | H29: =H22*Inputs!G27 -> 113 | I29: =I22*Inputs!H27 -> 334 | J29: =J22*Inputs!I27 -> 196.21574 | K29: =K22*Inputs!J27 -> 202.44447 | ... N29: =N22*Inputs!M27 -> 222.52378
B30: - CAPEX | D30: =D22*Inputs!C26 -> 718 | E30: =E22*Inputs!D26 -> 727 | F30: =F22*Inputs!E26 -> 895 | G30: =G22*Inputs!F26 -> 957 | H30: =H22*Inputs!G26 -> 810 | I30: =I22*Inputs!H26 -> 1231 | J30: =J22*Inputs!I26 -> 1317.0166 | K30: =K22*Inputs!J26 -> 1564.1365 | ... N30: =N22*Inputs!M26 -> 2396.3018
B31: FCF | D31: =D27+D28-D29-D30 -> 2848.2775 | E31: =E27+E28-E29-E30 -> 4169.2705 | F31: =F27+F28-F29-F30 -> 1151.1023 | G31: =G27+G28-G29-G30 -> 6809.5102 | H31: =H27+H28-H29-H30 -> 4821.2782 | I31: =I27+I28-I29-I30 -> 5611.4478 | J31: =J27+J28-J29-J30 -> 3596.1005 | K31: =K27+K28-K29-K30 -> 3504.9441 | ... N31: =N27+N28-N29-N30 -> 3175.5518
B32: Discount Factor | J32: =1/(1+$C$11)^1 -> 0.94975563 | K32: =1/(1+$C$11)^2 -> 0.90203576 | L32: =1/(1+$C$11)^3 -> 0.85671354 | M32: =1/(1+$C$11)^4 -> 0.81366851 | N32: =1/(1+$C$11)^5 -> 0.77278625
B33: Discounted FCF | J33: =J31*J32 -> 3415.4167 | K33: =K31*K32 -> 3161.5849 | L33: =L31*L32 -> 2916.973 | M33: =M31*M32 -> 2681.231 | N33: =N31*N32 -> 2454.0227
B36: Terminal Value Calculation
B38: Terminal Value
B39: Terminal Year | C39: FY2027
B40: Terminal Cash Flow | C40: =N31*(1+C41) -> 3239.0628
B41: Terminal Growth Rate | C41: 0.02 | D41: Assumption 26
B42: Discount Rate | C42: =C11 -> 0.052902418
B43: Terminal Value | C43: =C40/(C42-C41) -> 98444.521
B44: PV of Terminal Value | C44: =C43/(1+C42)^5 -> 76076.571
B46: Value per Share
B47: Enterprise Value | C47: =SUM(J33:N33)+C44 -> 90705.8
B48: Debt | C48: =WACC!B3 -> 18520.296
B49: Cash | C49: ='Balance Sheet'!G11 -> 2404
B51: FCFE | C51: =C47-C48+C49 -> 74589.503
B52: No. of Shares | C52: =Comparables!G8 -> 284.77109
B53: Value per Share | C53: =C51/C52 -> 261.92794
B54: Value per Share Adjusted to Jan 24, 2022:
B55: Enterprise Value, Jan 24, 2022 | C55: =J31/(1+C11)^(249/365)+K31/(1+C11)^(1+249/365)+L31/(1+C11)^(2+249/365)+M31/(1+C11)^(3+249/365)+N31/(1+C11)^(4+249/365)+C43/(1+C11)^(4+249/365) -> 92204.09 | D55: Assumption 27
B56: FCFE, Jan 24, 2022 | C56: =C55-C48+C49 -> 76087.794 | D56: Assumption 28
B57: No. of Shares | C57: 284.77
B58: Value per Share, Jan 24, 2022 | C58: =C56/C57 -> 267.19034
B59: Actual Value per Share on Jan 24, 2022 | C59: 252.72
B60: Over (Under) Valued | C60: =C59-C58 -> -14.470342
B63: Implied Equity Value, and Share Price
B65: Valuation by Multiples - PE LTM
B66: Peer Group's PE Ratio LTM | C66: =Comparables!F30 -> 45.642509
B67: LTM Net Income | C67: ='Income Statement'!G52 -> 2002
B68: Equity Value | C68: =C66*C67 -> 91376.303
B69: Number of Shares Outstanding | C69: =Comparables!G8 -> 284.77109
B70: Implied Share Price | C70: =C68/C69 -> 320.87633
B71: Actual Share Price Jan 24th, 2022 | C71: 252.7
B72: Over (under) valued | C72: =C71-C70 -> -68.176335
B74: Valuation by Multiples - EV/EBIT
B75: Peer Group's EV/EBIT | C75: =Comparables!L16 -> 34.40853
B76: BDX EBIT | C76: =Comparables!J8 -> 2815
B77: Enterprise Value | C77: =C75*C76 -> 96860.012
B78: Number of Shares Outstanding | C78: =Comparables!G8 -> 284.77109
B79: Implied Share Price | C79: =C77/C78 -> 340.13289
B80: Actual Share Price Jan 24th, 2022 | C80: 252.7
B81: Over (under) valued | C81: =C80-C79 -> -87.432886
B83: Valuation by Multiples - Conclusion
B84: Concluded Fair Value | C84: =AVERAGE(C70,C79) -> 330.50461
B85: Actual Share Price Jan 24th, 2022 | C85: 252.7
B86: Over (under) valued | C86: =C85-C84 -> -77.80461
B89: Share Price Sensitivity Analysis
G93: WACC
C95: 267.19 | D95: 0.0379 | E95: 0.0429 | F95: 0.0479 | G95: 0.0529 | H95: 0.0579 | I95: 0.0629 | J95: 0.0679
C96: 0.005 | D96: 283.72 | E96: 239.79 | F96: 206.09 | G96: 179.41 | H96: 157.77 | I96: 139.86 | J96: 124.8
C97: 0.01 | D97: 336.68 | E97: 278.09 | F97: 234.95 | G97: 201.85 | H97: 175.66 | I97: 154.4 | J97: 136.82
C98: 0.015 | D98: 412.76 | E98: 330.12 | F98: 272.58 | G98: 230.21 | H98: 197.71 | I98: 171.98 | J98: 151.11
B99: Terminal Growth | C99: 0.02 | D99: 531.34 | E99: 404.87 | F99: 323.7 | G99: 267.19 | H99: 225.58 | I99: 193.65 | J99: 168.38
C100: 0.025 | D100: 741.83 | E100: 521.37 | F100: 397.14 | G100: 317.42 | H100: 261.92 | I100: 221.04 | J100: 189.68
C101: 0.03 | D101: 1218.67 | E101: 728.16 | F101: 511.61 | G101: 389.59 | H101: 311.28 | I101: 256.76 | J101: 216.6
C102: 0.035 | D102: 3338.41 | E102: 1196.64 | F102: 714.79 | G102: 502.07 | H102: 382.2 | I102: 305.27 | J102: 251.71
G106: Cost of Equity
C108: 267.19 | D108: 0.0463 | E108: 0.0513 | F108: 0.0563 | G108: 0.0613 | H108: 0.0663 | I108: 0.0713 | J108: 0.0763
C109: 0.0091 | D109: 511.76 | E109: 412.26 | F109: 342.78 | G109: 291.52 | H109: 252.13 | I109: 220.92 | J109: 195.58
C110: 0.0141 | D110: 489 | E110: 396.76 | F110: 331.55 | G110: 283 | H110: 245.46 | I110: 215.55 | J110: 191.16
C111: 0.0191 | D111: 468.02 | E111: 382.26 | F111: 320.94 | G111: 274.9 | H111: 239.07 | I111: 210.38 | J111: 186.89
B112: Cost of Debt | C112: 0.0241 | D112: 448.61 | E112: 368.69 | F112: 310.91 | G112: 267.19 | H112: 232.95 | I112: 205.41 | J112: 182.78
C113: 0.0291 | D113: 430.61 | E113: 355.94 | F113: 301.41 | G113: 259.84 | H113: 227.09 | I113: 200.63 | J113: 178.81
C114: 0.0341 | D114: 413.87 | E114: 343.95 | F114: 292.4 | G114: 252.82 | H114: 221.47 | I114: 196.03 | J114: 174.97
C115: 0.0391 | D115: 398.26 | E115: 332.64 | F115: 283.84 | G115: 246.11 | H115: 216.08 | I115: 191.59 | J115: 171.26
G119: Terminal Growth
C121: 267.19 | D121: 0.005 | E121: 0.01 | F121: 0.015 | G121: 0.02 | H121: 0.025 | I121: 0.03 | J121: 0.035
C122: 0.36 | D122: 182.9 | E122: 206.13 | F122: 235.6 | G122: 274.24 | H122: 327.08 | I122: 403.75 | J122: 525.04
C123: 0.31 | D123: 181.72 | E123: 204.69 | F123: 233.78 | G123: 271.85 | H123: 323.81 | I123: 398.93 | J123: 517.17
B124: Tax Rate | C124: 0.26 | D124: 180.56 | E124: 203.26 | F124: 231.99 | G124: 269.5 | H124: 320.59 | I124: 394.21 | J124: 509.52
C125: 0.21 | D125: 179.41 | E125: 201.85 | F125: 230.21 | G125: 267.19 | H125: 317.42 | I125: 389.59 | J125: 502.07
C126: 0.16 | D126: 178.27 | E126: 200.46 | F126: 228.46 | G126: 264.91 | H126: 314.31 | I126: 385.06 | J126: 494.81
C127: 0.11 | D127: 177.14 | E127: 199.08 | F127: 226.73 | G127: 262.66 | H127: 311.25 | I127: 380.63 | J127: 487.75
...

Sheet Comparables
A3: Comps Tables - FactSet RBICS Sub-Sector - General Medical Devices | E3: Assumption 28
A4: Selected Financials
D5: Market Data ($) | I5: Financial ($) | L5: Valuation (x)
A6: Company | C6: Fiscal | G6: Shares Out | H6: Shares Out | L6: EV/ | M6: EV/
A7: Name | B7: Ticker | C7: Period | D7: Price | E7: Mkt Cap (M) | F7: EV (M) | G7: (M) | H7: Diluted (M) | I7: Sales (M) | J7: EBIT (M) | K7: EBITDA (M) | L7: EBIT | M7: EBITDA
A8: Becton, Dickinson | B8: BDX-US | C8: 12/31/2021 | D8: 267.60001 | E8: 76204.737 | F8: 91575.734 | G8: 284.77109 | H8: 286.723 | I8: 19927 | J8: 2815 | K8: 5090 | L8: 32.531344 | M8: 17.991303
A9: Edwards Lifesciences | B9: EW-US | C9: 12/2021 | D9: 111.55 | E9: 69518.794 | F9: 68740.797 | G9: 623.20746 | H9: 631.2 | I9: 5232.5 | J9: 1610.4 | K9: 1773.7 | L9: 42.685544 | M9: 38.755596
A10: Boston Scientific | B10: BSX-US | C10: 12/2021 | D10: 44.32 | E10: 63232.44 | F10: 70644.438 | G10: 1426.7247 | H10: 1433.8 | I10: 11888 | J10: 1922 | K10: 3015 | L10: 36.755692 | M10: 23.430992
A11: Stryker Corp | B11: SYK-US | C11: 12/2021 | D11: 265.79001 | E11: 100347.6 | F11: 110229.6 | G11: 377.54468 | H11: 382.3 | I11: 17108 | J11: 3661 | K11: 4651 | L11: 30.109151 | M11: 23.700194
A12: Intuitive Surgical | B12: ISRG-US | C12: 12/2021 | D12: 283.28 | E12: 101752.72 | F12: 97686.117 | G12: 359.19482 | H12: 365.8 | I12: 5710.1 | J12: 1821 | K12: 2138 | L12: 53.644217 | M12: 45.690421
A13: Baxter Intl | B13: BAX-US | C13: 12/2021 | D13: 79.050003 | E13: 39706.314 | F13: 55104.312 | G13: 502.29361 | H13: 508 | I13: 12784 | J13: 2083 | K13: 2973 | L13: 26.454303 | M13: 18.534919
A14: Danaher | B14: DHR-US | C14: 12/2021 | D14: 289.26999 | E14: 206930.02 | F14: 230894.02 | G14: 715.3526 | H14: 736.8 | I14: 29453 | J14: 8050 | K14: 10218 | L14: 28.682487 | M14: 22.596792
A15: Abbott Laboratories | B15: ABT-US | C15: 12/2021 | D15: 121.76 | E15: 215306.63 | F15: 224530.62 | G15: 1768.287 | H15: 1789 | I15: 43075 | J15: 9200 | K15: 12738 | L15: 24.405503 | M15: 17.626835
A16: Average | L16: 34.40853 | M16: 26.040882
A17: Median | L17: 31.320248 | M17: 23.013892
A18: Valuation
F19: P/E (x) | I19: EV/ (x) | L19: Financial ($)
A20: Company | C20: Fiscal | D20: FY1
A21: Name | B21: Ticker | C21: Period | D21: Date | E21: EV (M) | F21: Actual | G21: FY1 | H21: FY2 | I21: Sales | J21: EBIT | K21: EBITDA | L21: Sales (M) | M21: EBIT (M) | N21: EBITDA (M)
A22: Becton, Dickinson | B22: BDX-US | C22: 12/31/2021 | D22: 09/2022 | E22: 91575.734 | F22: 46.246371 | G22: 20.708977 | H22: 19.176928 | I22: 4.59556 | J22: 32.531344 | K22: 17.991303 | L22: 19927 | M22: 2815 | N22: 5090
A23: Edwards Lifesciences | B23: EW-US | C23: 12/2021 | D23: 12/2022 | E23: 68740.797 | F23: 46.844161 | G23: 43.832638 | H23: 38.795483 | I23: 13.137277 | J23: 42.685544 | K23: 38.755596 | L23: 5232.5 | M23: 1610.4 | N23: 1773.7
A24: Boston Scientific | B24: BSX-US | C24: 12/2021 | D24: 12/2022 | E24: 70644.438 | F24: 64.512373 | G24: 25.021961 | H24: 22.077976 | I24: 5.9425 | J24: 36.755692 | K24: 23.430992 | L24: 11888 | M24: 1922 | N24: 3015
A25: Stryker Corp | B25: SYK-US | C25: 12/2021 | D25: 12/2022 | E25: 110229.6 | F25: 50.958626 | G25: 27.143648 | H25: 24.251787 | I25: 6.443161 | J25: 30.109151 | K25: 23.700194 | L25: 17108 | M25: 3661 | N25: 4651
A26: Intuitive Surgical | B26: ISRG-US | C26: 12/2021 | D26: 12/2022 | E26: 97686.117 | F26: 60.791004 | G26: 56.469055 | H26: 47.832645 | I26: 17.107602 | J26: 53.644217 | K26: 45.690421 | L26: 5710.1 | M26: 1821 | N26: 2138
A27: Baxter Intl | B27: BAX-US | C27: 12/2021 | D27: 12/2022 | E27: 55104.312 | F27: 31.274727 | G27: 18.39086 | H27: 16.09816 | I27: 4.310412 | J27: 26.454303 | K27: 18.534919 | L27: 12784 | M27: 2083 | N27: 2973
A28: Danaher | B28: DHR-US | C28: 12/2021 | D28: 12/2022 | E28: 230894.02 | F28: 33.58021 | G28: 27.707012 | H28: 26.158239 | I28: 7.839406 | J28: 28.682487 | K28: 22.596792 | L28: 29453 | M28: 8050 | N28: 10218
A29: Abbott Laboratories | B29: ABT-US | C29: 12/2021 | D29: 12/2022 | E29: 224530.62 | F29: 30.932602 | G29: 25.110802 | H29: 23.737774 | I29: 5.212551 | J29: 24.405503 | K29: 17.626835 | L29: 43075 | M29: 9200 | N29: 12738
A30: Average | F30: 45.642509 | G30: 30.548119 | H30: 27.266124 | I30: 8.073559 | J30: 34.40853 | K30: 26.040882
A31: Median | F31: 46.545266 | G31: 26.127225 | H31: 23.994781 | I31: 6.19283 | J31: 31.320248 | K31: 23.013892

Sheet BDX-USA
A1: Becton, Dickinson and Company
A2: BDX 075887109 2087807 NYSE Common stock
A5: Instrument ID | B5: Description | C5: Balance Sheet Amt Out (USD) | D5: Current Amt Out (USD) | E5: Coupon Rate | F5: Coupon Type | G5: Issue Date | H5: Maturity Date | I5: Issue Curr | J5: Seniority | K5: Price | L5: YTW | M5: OAS (LIBOR)
A6: ST Debt | C6: 1064 | D6: 1064
A7: - | B7: Current Portion Of LTD | C7: 1064 | D7: 1064 | E7: - | F7: - | G7: - | H7: - | I7: USD | J7: Other | K7: - | L7: - | M7: -
A8: Revolving Credit | C8: 0 | D8: 0
A9: FDS1OTGB4 | B9: Senior Unsec. Revolving Credit Facility | C9: 0 | D9: 0 | E9: - | F9: Variable | G9: 09/2021 | H9: 09/2026 | I9: USD | J9: SNR Unsec | K9: - | L9: - | M9: - | N9: _
A10: Notes/Bonds | C10: 17509.9 | D10: 17509.9
A11: 075887BU2 | B11: Becton Dickinson & Co - FRN | C11: 500 | D11: 500 | E11: - | F11: Variable | G11: 06/2017 | H11: 06/2022 | I11: USD | J11: SNR Unsec | K11: 100.08 | L11: 1.27 | M11: 40.1 | N11: _
A12: 075887BN8 | B12: Becton Dickinson & Co - 500M EUR | C12: 568.6 | D12: 568.6 | E12: 0.01 | F12: Fixed | G12: 12/2016 | H12: 12/2022 | I12: EUR | J12: SNR Unsec | K12: 100.7 | L12: 0.06 | M12: 37.33 | N12: _
A13: 075887CH0 | B13: Becton Dickinson & Co - MTN - 300M EUR | C13: 341.2 | D13: 341.2 | E13: 0.01401 | F13: Fixed | G13: 05/2018 | H13: 05/2023 | I13: EUR | J13: SNR Unsec | K13: 101.33 | L13: 0.19 | M13: 31.33 | N13: _
A14: 075887CM9 | B14: Becton Dickinson & Co - 400M EUR | C14: 454.9 | D14: 454.9 | E14: - | F14: Fixed | G14: 08/2021 | H14: 08/2023 | I14: EUR | J14: SNR Unsec | K14: 99.43 | L14: 0.41 | M14: 37.84
A15: 07589LAB3 | B15: Becton Dickinson Euro Finance SARL - 800M EUR | C15: 909.8 | D15: 909.8 | E15: 0.00632 | F15: Fixed | G15: 06/2019 | H15: 06/2023 | I15: EUR | J15: SNR Unsec | K15: 100.58 | L15: 0.12 | M15: 19.93 | N15: _
A16: 075887BL2 | B16: Becton Dickinson & Co | C16: 143.6 | D16: 143.6 | E16: 0.03875 | F16: Fixed | G16: 04/2015 | H16: 05/2024 | I16: USD | J16: SNR Unsec | K16: 101.59 | L16: 3.01 | M16: 80.92 | N16: _
A17: 075887BF5 | B17: Becton Dickinson & Co | C17: 875 | D17: 875 | E17: 0.03734 | F17: Fixed | G17: 12/2014 | H17: 12/2024 | I17: USD | J17: SNR Unsec | K17: 102.03 | L17: 2.88 | M17: 59.02 | N17: _
A18: 075887BV0 | B18: Becton Dickinson & Co | C18: 997.7 | D18: 997.7 | E18: 0.03363 | F18: Fixed | G18: 06/2017 | H18: 06/2024 | I18: USD | J18: SNR Unsec | K18: 101.4 | L18: 2.65 | M18: 42.34
A19: 075887CG2 | B19: Becton Dickinson & Co - 250M GBP | C19: 338.6 | D19: 338.6 | E19: 0.0302 | F19: Fixed | G19: 05/2018 | H19: 05/2025 | I19: GBP | J19: SNR Unsec | K19: 101.66 | L19: 2.43 | M19: 57.91 | N19: _
A20: 075887CN7 | B20: Becton Dickinson & Co - 500M EUR | C20: 568.6 | D20: 568.6 | E20: 0.00034 | F20: Fixed | G20: 08/2021 | H20: 08/2025 | I20: EUR | J20: SNR Unsec | K20: 96.85 | L20: 0.98 | M20: 43.44 | N20: _
A21: 067383AA7 | B21: CR Bard Inc | C21: 12.8 | D21: 12.8 | E21: 0.067 | F21: Fixed | G21: 12/1996 | H21: 12/2026 | I21: USD | J21: SNR Unsec | K21: 107.32 | L21: 4.93 | M21: 269.44 | N21: _
A22: 075887CE7 | B22: Becton Dickinson & Co | C22: 134 | D22: 134 | E22: 0.067 | F22: Fixed | G22: 04/2018 | H22: 12/2026 | I22: USD | J22: SNR Unsec | K22: 114.29 | L22: 3.39 | M22: 114.65 | N22: _
A23: 075887BP3 | B23: Becton Dickinson & Co - 500M EUR | C23: 568.6 | D23: 568.6 | E23: 0.019 | F23: Fixed | G23: 12/2016 | H23: 12/2026 | I23: EUR | J23: SNR Unsec | K23: 102.97 | L23: 1.21 | M23: 52.51 | N23: _
A24: 07589LAC1 | B24: Becton Dickinson Euro Finance SARL - 600M EUR | C24: 682.3 | D24: 682.3 | E24: 0.01208 | F24: Fixed | G24: 06/2019 | H24: 06/2026 | I24: EUR | J24: SNR Unsec | K24: 100.02 | L24: 1.2 | M24: 53.93 | N24: _
A25: 075887AN9 | B25: Becton Dickinson & Co | C25: 168 | D25: 168 | E25: 0.07 | F25: Fixed | G25: 07/1997 | H25: 08/2027 | I25: USD | J25: SNR Unsec | K25: 117.89 | L25: 3.33 | M25: 110.02 | N25: _
A26: 075887BW8 | B26: Becton Dickinson & Co | C26: 1725 | D26: 1725 | E26: 0.037 | F26: Fixed | G26: 06/2017 | H26: 06/2027 | I26: USD | J26: SNR Unsec | K26: 102.53 | L26: 3.14 | M26: 88.9
A27: 075887AQ2 | B27: Becton Dickinson & Co | C27: 167.1 | D27: 167.1 | E27: 0.067 | F27: Fixed | G27: 08/1998 | H27: 08/2028 | I27: USD | J27: SNR Unsec | K27: 117.2 | L27: 3.65 | M27: 141.33 | N27: _
A28: L076BMAB2 | B28: Becton Dickinson Euro Finance SARL - 900M EUR | C28: 1023.5 | D28: 1023.5 | E28: 0.00334 | F28: Fixed | G28: 08/2021 | H28: 08/2028 | I28: EUR | J28: SNR Unsec | K28: 92.48 | L28: 1.57 | M28: 76.54 | N28: _
A29: 075887CJ6 | B29: Becton Dickinson & Co | C29: 750 | D29: 750 | E29: 0.02823 | F29: Fixed | G29: 05/2020 | H29: 05/2030 | I29: USD | J29: SNR Unsec | K29: 95.71 | L29: 3.43 | M29: 117.53 | N29: _
A30: 075887CL1 | B30: Becton Dickinson & Co | C30: 1000 | D30: 1000 | E30: 0.01957 | F30: Fixed | G30: 02/2021 | H30: 02/2031 | I30: USD | J30: SNR Unsec | K30: 89 | L30: 3.4 | M30: 114.19 | N30: _
A31: 07589LAD9 | B31: Becton Dickinson & Co - 600M EUR | C31: 682.3 | D31: 682.3 | E31: 0.01213 | F31: Fixed | G31: 02/2021 | H31: 02/2036 | I31: EUR | J31: SNR Unsec | K31: 88.1 | L31: 2.2 | M31: 108.15 | N31: _
A32: 075887AV1 | B32: Becton Dickinson & Co | C32: 250 | D32: 250 | E32: 0.06 | F32: Fixed | G32: 05/2009 | H32: 05/2039 | I32: USD | J32: SNR Unsec | K32: 119.82 | L32: 4.35 | M32: 202.37 | N32: _
A33: 075887AX7 | B33: Becton Dickinson & Co | C33: 125 | D33: 125 | E33: 0.05 | F33: Fixed | G33: 11/2010 | H33: 11/2040 | I33: USD | J33: SNR Unsec | K33: 108.32 | L33: 4.34 | M33: 201.12 | N33: _
A34: L076BMAA4 | B34: Becton Dickinson Euro Finance SARL - 900M EUR | C34: 1023.5 | D34: 1023.5 | E34: 0.01336 | F34: Fixed | G34: 08/2021 | H34: 08/2041 | I34: EUR | J34: SNR Unsec | K34: 82.4 | L34: 2.48 | M34: 136.79 | N34: _
A35: 075887BM0 | B35: Becton Dickinson & Co | C35: 224.9 | D35: 224.9 | E35: 0.04875 | F35: Fixed | G35: 04/2015 | H35: 05/2044 | I35: USD | J35: SNR Unsec | K35: 108.04 | L35: 4.3 | M35: 196.74 | N35: _
A36: 075887BG3 | B36: Becton Dickinson & Co | C36: 1025 | D36: 1025 | E36: 0.04685 | F36: Fixed | G36: 12/2014 | H36: 12/2044 | I36: USD | J36: SNR Unsec | K36: 107.85 | L36: 4.14 | M36: 181.1
A37: 075887BX6 | B37: Becton Dickinson & Co | C37: 1500 | D37: 1500 | E37: 0.04669 | F37: Fixed | G37: 06/2017 | H37: 06/2047 | I37: USD | J37: SNR Unsec | K37: 108.67 | L37: 4.11 | M37: 179.48
A38: 075887CK3 | B38: Becton Dickinson & Co | C38: 750 | D38: 750 | E38: 0.03794 | F38: Fixed | G38: 05/2020 | H38: 05/2050 | I38: USD | J38: SNR Unsec | K38: 95.38 | L38: 4.07 | M38: 178.11 | N38: _
A39: Other | C39: -85.9 | D39: -85.9
A40: - | B40: Unamortized Issuance Costs - Senior Unsecured Notes | C40: -85.9 | D40: -85.9 | E40: - | F40: - | G40: - | H40: - | I40: USD | J40: Other | K40: - | L40: - | M40: -
B41: LT Debt Total | C41: 17424
B42: Current Portion of LTD | C42: -1064
B43: Net LT Debt Total | C43: 16360
B44: ST Debt Total | C44: 1064
B45: Total Debt | C45: 17424 | D45: 17424
A46: Data as of 18 Mar '22 | B46: Amount Outstanding in millions of USD
A47: Source: FactSet DCS and FactSet Fixed Income
A48: * The current total debt outstanding value is not considered a reconciled amount. Activity is determined on a transactional basis and there can be events that may affect amounts that are not disclosed until the next filing date.

Sheet Cost of Debt
A1: Becton, Dickinson and Company | C1: Book Value | D1: Price(as % of par) | E1: Market Value | F1: MV percentage of Total Debt | G1: YTW(%)
A2: BDX 075887109 2087807 NYSE Common stock
A5: Instrument ID
A6: ST Debt | C6: 1064 | D6: - | E6: =C6 -> 1064 | F6: =E6/$E$41 -> 0.057450485 | G6: 0 | H6: =F6*G6 -> 0
A8: Notes/Bonds
A9: 075887BU2 | C9: 500 | D9: 100.08 | E9: =C9*(D9/100) -> 500.4 | F9: =E9/$E$41 -> 0.027019006 | G9: 1.27 | H9: =F9*G9 -> 0.034314138
A10: 075887BN8 | C10: 568.6 | D10: 100.7 | E10: =C10*(D10/100) -> 572.5802 | F10: =E10/$E$41 -> 0.030916363 | G10: 0.06 | H10: =F10*G10 -> 0.0018549818
A11: 075887CH0 | C11: 341.2 | D11: 101.33 | E11: =C11*(D11/100) -> 345.73796 | F11: =E11/$E$41 -> 0.018668058 | G11: 0.19 | H11: =F11*G11 -> 0.003546931
A12: 075887CM9 | C12: 454.9 | D12: 99.43 | E12: =C12*(D12/100) -> 452.30707 | F12: =E12/$E$41 -> 0.024422237 | G12: 0.41 | H12: =F12*G12 -> 0.010013117
A13: 07589LAB3 | C13: 909.8 | D13: 100.58 | E13: =C13*(D13/100) -> 915.07684 | F13: =E13/$E$41 -> 0.049409406 | G13: 0.12 | H13: =F13*G13 -> 0.0059291287
A14: 075887BL2 | C14: 143.6 | D14: 101.59 | E14: =C14*(D14/100) -> 145.88324 | F14: =E14/$E$41 -> 0.0078769387 | G14: 3.01 | H14: =F14*G14 -> 0.023709586
A15: 075887BF5 | C15: 875 | D15: 102.03 | E15: =C15*(D15/100) -> 892.7625 | F15: =E15/$E$41 -> 0.048204547 | G15: 2.88 | H15: =F15*G15 -> 0.1388291
A16: 075887BV0 | C16: 997.7 | D16: 101.4 | E16: =C16*(D16/100) -> 1011.6678 | F16: =E16/$E$41 -> 0.054624817 | G16: 2.65 | H16: =F16*G16 -> 0.14475577
A17: 075887CG2 | C17: 338.6 | D17: 101.66 | E17: =C17*(D17/100) -> 344.22076 | F17: =E17/$E$41 -> 0.018586137 | G17: 2.43 | H17: =F17*G17 -> 0.045164312
A18: 075887CN7 | C18: 568.6 | D18: 96.85 | E18: =C18*(D18/100) -> 550.6891 | F18: =E18/$E$41 -> 0.029734357 | G18: 0.98 | H18: =F18*G18 -> 0.02913967
A19: 067383AA7 | C19: 12.8 | D19: 107.32 | E19: =C19*(D19/100) -> 13.73696 | F19: =E19/$E$41 -> 0.00074172463 | G19: 4.93 | H19: =F19*G19 -> 0.0036567024
A20: 075887CE7 | C20: 134 | D20: 114.29 | E20: =C20*(D20/100) -> 153.1486 | F20: =E20/$E$41 -> 0.0082692305 | G20: 3.39 | H20: =F20*G20 -> 0.028032691
... A36: 075887CK3 | C36: 750 | D36: 95.38 | E36: =C36*(D36/100) -> 715.35 | F36: =E36/$E$41 -> 0.038625192 | G36: 4.07 | H36: =F36*G36 -> 0.15720453
A37: Other | C37: -85.9
A38: - | C38: -85.9
B39: LT Debt Total | E39: =SUM(E9:E36) -> 17456.296 | F39: =SUM(F6:F36) -> 1
B40: ST Debt Total | E40: =E6 -> 1064 | G40: Cost of debt | H40: =SUM(H9:H36) -> 2.4109514
B41: Total Debt | E41: =E40+E39 -> 18520.296

Sheet Cost of Equity
A1: Date | B1: Open | C1: High | D1: Low | E1: Close | F1: Adj Close | G1: Volume | H1: Return for Beckton dickinson | J1: Date | K1: Open | L1: High | M1: Low | N1: Close* | O1: Adj Close** | P1: Volume | R1: Return for Beckton dickinson | S1: Market Return
A2: 42826 | B2: 184 | C2: 187.2 | D2: 175.66 | E2: 186.97 | F2: 174.96549 | G2: 31303400 | H2: =(F3-F2)/F2 -> 0.012087515 | J2: 42826 | K2: 2362.34 | L2: 2398.16 | M2: 2328.95 | N2: 2384.2 | O2: 2384.2 | P2: 65265670000 | R2: 0.012087515 | S2: =(O3-O2)/O2 -> 0.01157621 | W2: SUMMARY OUTPUT
A3: 42856 | B3: 186.38001 | C3: 190.71001 | D3: 177.64 | E3: 189.23 | F3: 177.08038 | G3: 59044400 | H3: =(F4-F3)/F3 -> 0.031073301 | J3: 42856 | K3: 2388.5 | L3: 2418.71 | M3: 2352.72 | N3: 2411.8 | O3: 2411.8 | P3: 79607170000 | R3: 0.031073301 | S3: =(O4-O3)/O3 -> 0.004813832
A4: 42887 | B4: 188.36999 | C4: 196.59 | D4: 188.3 | E4: 195.11 | F4: 182.58285 | G4: 31272500 | H4: =(F5-F4)/F4 -> 0.036180013 | J4: 42887 | K4: 2415.65 | L4: 2453.82 | M4: 2405.7 | N4: 2423.41 | O4: 2423.41 | P4: 81002490000 | R4: 0.036180013 | S4: =(O5-O4)/O4 -> 0.019348769 | W4: Regression Statistics
A5: 42917 | B5: 195.78999 | C5: 206.63001 | D5: 194.22 | E5: 201.39999 | F5: 189.1887 | G5: 22497400 | H5: =(F6-F5)/F5 -> -0.0097319288 | J5: 42917 | K5: 2431.39 | L5: 2484.04 | M5: 2407.7 | N5: 2470.3 | O5: 2470.3 | P5: 63169400000 | R5: -0.0097319288 | S5: =(O6-O5)/O5 -> 0.00054649233 | W5: Multiple R | X5: 0.48193512
A6: 42948 | B6: 201.7 | C6: 202.89999 | D6: 192.34 | E6: 199.44 | F6: 187.34753 | G6: 25729600 | H6: =(F7-F6)/F6 -> -0.017498848 | J6: 42948 | K6: 2477.1 | L6: 2490.87 | M6: 2417.35 | N6: 2471.65 | O6: 2471.65 | P6: 70616030000 | R6: -0.017498848 | S6: =(O7-O6)/O6 -> 0.019302895 | W6: R Square | X6: 0.23226146
A7: 42979 | B7: 199.44 | C7: 204.86 | D7: 191.53 | E7: 195.95 | F7: 184.06917 | G7: 23085100 | H7: =(F8-F7)/F7 -> 0.06883074 | J7: 42979 | K7: 2474.42 | L7: 2519.44 | M7: 2446.55 | N7: 2519.36 | O7: 2519.36 | P7: 66337980000 | R7: 0.06883074 | S7: =(O8-O7)/O7 -> 0.022188175 | W7: Adjusted R Square | X7: 0.21902458
A8: 43009 | B8: 196.91 | C8: 214.72 | D8: 193.05 | E8: 208.67 | F8: 196.73879 | G8: 25966300 | H8: =(F9-F8)/F8 -> 0.093640712 | J8: 43009 | K8: 2521.2 | L8: 2582.98 | M8: 2520.4 | N8: 2575.26 | O8: 2575.26 | P8: 70871570000 | R8: 0.093640712 | S8: =(O9-O8)/O8 -> 0.028082601 | W8: Standard Error | X8: 0.055500731
A9: 43040 | B9: 207.53 | C9: 228.8 | D9: 203.99 | E9: 228.21001 | F9: 215.16154 | G9: 26588300 | H9: =(F10-F9)/F9 -> -0.062004379 | J9: 43040 | K9: 2583.21 | L9: 2657.74 | M9: 2557.45 | N9: 2647.58 | O9: 2647.58 | P9: 73173260000 | R9: -0.062004379 | S9: =(O10-O9)/O9 -> 0.0098316198 | W9: Observations | X9: 60
A10: 43070 | B10: 228.27 | C10: 229.69 | D10: 213.95 | E10: 214.06 | F10: 201.82059 | G10: 25016300 | H10: =(F11-F10)/F10 -> 0.13881708 | J10: 43070 | K10: 2645.1 | L10: 2694.97 | M10: 2605.52 | N10: 2673.61 | O10: 2673.61 | P10: 65251190000 | R10: 0.13881708 | S10: =(O11-O10)/O10 -> 0.056178725
A11: 43101 | B11: 215.09 | C11: 248.39 | D11: 215.09 | E11: 242.94 | F11: 229.83673 | G11: 31718400 | H11: =(F12-F11)/F11 -> -0.086112006 | J11: 43101 | K11: 2683.73 | L11: 2872.87 | M11: 2682.36 | N11: 2823.81 | O11: 2823.81 | P11: 76860120000 | R11: -0.086112006 | S11: =(O12-O11)/O11 -> -0.03894738 | W11: ANOVA
A12: 43132 | B12: 241.08 | C12: 243.51 | D12: 209.91 | E12: 222.02 | F12: 210.04503 | G12: 29950400 | H12: =(F13-F12)/F12 -> -0.0239617 | J12: 43132 | K12: 2816.45 | L12: 2835.96 | M12: 2532.69 | N12: 2713.83 | O12: 2713.83 | P12: 79579410000 | R12: -0.0239617 | S12: =(O13-O12)/O12 -> -0.026884514 | X12: df | Y12: SS | Z12: MS | AA12: F | AB12: Significance F
A13: 43160 | B13: 221.60001 | C13: 227.8 | D13: 210.39 | E13: 216.7 | F13: 205.01199 | G13: 25411700 | H13: =(F14-F13)/F13 -> 0.073680085 | J13: 43160 | K13: 2715.22 | L13: 2801.9 | M13: 2585.89 | N13: 2640.87 | O13: 2640.87 | P13: 76369800000 | R13: 0.073680085 | S13: =(O14-O13)/O13 -> 0.002718801 | W13: Regression | X13: 1 | Y13: 0.054049191 | Z13: 0.054049191 | AA13: 17.546552 | AB13: 9.6648145e-05
A14: 43191 | B14: 215.99 | C14: 236.13001 | D14: 210.21001 | E14: 231.86999 | F14: 220.11729 | G14: 23710200 | H14: =(F15-F14)/F14 -> -0.044335394 | J14: 43191 | K14: 2633.45 | L14: 2717.49 | M14: 2553.8 | N14: 2648.05 | O14: 2648.05 | P14: 69648590000 | R14: -0.044335394 | S14: =(O15-O14)/O14 -> 0.021608353 | W14: Residual | X14: 58 | Y14: 0.17865921 | Z14: 0.0030803311
A15: 43221 | B15: 230.77 | C15: 234.10001 | D15: 218.60001 | E15: 221.59 | F15: 210.35831 | G15: 28300000 | H15: =(F16-F15)/F15 -> 0.081095866 | J15: 43221 | K15: 2642.96 | L15: 2742.24 | M15: 2594.62 | N15: 2705.27 | O15: 2705.27 | P15: 75617280000 | R15: 0.081095866 | S15: =(O16-O15)/O15 -> 0.0048424002 | W15: Total | X15: 59 | Y15: 0.2327084
A16: 43252 | B16: 223.32001 | C16: 242.64 | D16: 223.03999 | E16: 239.56 | F16: 227.4175 | G16: 24768500 | H16: =(F17-F16)/F16 -> 0.048519618 | J16: 43252 | K16: 2718.7 | L16: 2791.47 | M16: 2691.99 | N16: 2718.37 | O16: 2718.37 | P16: 77439710000 | R16: 0.048519618 | S16: =(O17-O16)/O16 -> 0.036021586
A17: 43282 | B17: 237.45 | C17: 252.74 | D17: 235.33 | E17: 250.36999 | F17: 238.45171 | G17: 17394900 | H17: =(F18-F17)/F17 -> 0.045931984 | J17: 43282 | K17: 2704.95 | L17: 2848.03 | M17: 2698.95 | N17: 2816.29 | O17: 2816.29 | P17: 64542170000 | R17: 0.045931984 | S17: =(O18-O17)/O17 -> 0.030263219 | X17: Coefficients | Y17: Standard Error | Z17: t Stat | AA17: P-value | AB17: Lower 95% | AC17: Upper 95% | AD17: Lower 95.0% | AE17: Upper 95.0%
A18: 43313 | B18: 250.05 | C18: 262.67001 | D18: 239.8 | E18: 261.87 | F18: 249.40427 | G18: 18975800 | H18: =(F19-F18)/F18 -> -0.0033222447 | J18: 43313 | K18: 2821.17 | L18: 2916.5 | M18: 2796.34 | N18: 2901.52 | O18: 2901.52 | P18: 69238220000 | R18: -0.0033222447 | S18: =(O19-O18)/O18 -> 0.0042943009 | W18: Intercept | X18: 0.0010137532 | Y18: 0.0073955371 | Z18: 0.13707635 | AA18: 0.89144518 | AB18: -0.013790023 | AC18: 0.015817529 | AD18: -0.013790023 | AE18: 0.015817529
A19: 43344 | B19: 262.14002 | C19: 264.47 | D19: 253.21001 | E19: 261 | F19: 248.57568 | G19: 18208600 | H19: =(F20-F19)/F19 -> -0.11427926 | J19: 43344 | K19: 2896.96 | L19: 2940.91 | M19: 2864.12 | N19: 2913.98 | O19: 2913.98 | P19: 62492080000 | R19: -0.11427926 | S19: =(O20-O19)/O19 -> -0.069403359 | W19: Market Return | X19: 0.66554845 | Y19: 0.15888532 | Z19: 4.1888605 | AA19: 9.6648145e-05 | AB19: 0.34750492 | AC19: 0.98359198 | AD19: 0.34750492 | AE19: 0.98359198
A20: 43374 | B20: 262 | C20: 265.87 | D20: 225.34 | E20: 230.5 | F20: 220.16864 | G20: 26192800 | H20: =(F21-F20)/F20 -> 0.096529329 | J20: 43374 | K20: 2926.29 | L20: 2939.86 | M20: 2603.54 | N20: 2711.74 | O20: 2711.74 | P20: 91327930000 | R20: 0.096529329 | S20: =(O21-O20)/O20 -> 0.017859382
A21: 43405 | B21: 230.08 | C21: 253.32001 | D21: 225 | E21: 252.75 | F21: 241.42137 | G21: 26747700 | H21: =(F22-F21)/F21 -> -0.10852602 | J21: 43405 | K21: 2717.58 | L21: 2815.15 | M21: 2631.09 | N21: 2760.17 | O21: 2760.17 | P21: 80080110000 | R21: -0.10852602 | S21: =(O22-O21)/O21 -> -0.091776956 | W21: Risk Free | X21: 0.0247 | Y21: Assumption 29
A22: 43435 | B22: 253.94 | C22: 256.04001 | D22: 208.61999 | E22: 225.32001 | F22: 215.22087 | G22: 24604600 | H22: =(F23-F22)/F22 -> 0.11068164 | J22: 43435 | K22: 2790.5 | L22: 2800.18 | M22: 2346.58 | N22: 2506.85 | O22: 2506.85 | P22: 83522570000 | R22: 0.11068164 | S22: =(O23-O22)/O22 -> 0.078684405 | W22: Risk Premium | X22: 0.055 | Y22: Assumption 30
A23: 43466 | B23: 221.97 | C23: 249.86999 | D23: 210.72 | E23: 249.46001 | F23: 239.04187 | G23: 24353700 | H23: =(F24-F23)/F23 -> -0.0026858433 | J23: 43466 | K23: 2476.96 | L23: 2708.95 | M23: 2443.96 | N23: 2704.1 | O23: 2704.1 | P23: 80401630000 | R23: -0.0026858433 | S23: =(O24-O23)/O23 -> 0.02972893
A24: 43497 | B24: 249.27 | C24: 254 | D24: 237.75 | E24: 248.78999 | F24: 238.39984 | G24: 19094300 | H24: =(F25-F24)/F24 -> 0.0037782827 | J24: 43497 | K24: 2702.32 | L24: 2813.49 | M24: 2681.83 | N24: 2784.49 | O24: 2784.49 | P24: 70183430000 | R24: 0.0037782827 | S24: =(O25-O24)/O24 -> 0.017924288 | W24: Cost of Equity | X24: =X21+X19*X22 -> 0.061305165
A25: 43525 | B25: 250.53 | C25: 257.16 | D25: 238.21001 | E25: 249.73 | F25: 239.30058 | G25: 22842300 | H25: =(F26-F25)/F25 -> -0.033003601 | J25: 43525 | K25: 2798.22 | L25: 2860.31 | M25: 2722.27 | N25: 2834.4 | O25: 2834.4 | P25: 78596280000 | R25: -0.033003601 | S25: =(O26-O25)/O25 -> 0.039313435
A26: 43556 | B26: 250.88001 | C26: 253.83 | D26: 221.51 | E26: 240.74 | F26: 231.4028 | G26: 33077900 | H26: =(F27-F26)/F26 -> -0.030323081 | J26: 43556 | K26: 2848.63 | L26: 2949.52 | M26: 2848.63 | N26: 2945.83 | O26: 2945.83 | P26: 69604840000 | R26: -0.030323081 | S26: =(O27-O26)/O26 -> -0.065777726
A27: 43586 | B27: 240.28999 | C27: 240.73 | D27: 221.47 | E27: 233.44 | F27: 224.38596 | G27: 33310300 | H27: =(F28-F27)/F27 -> 0.079549373 | J27: 43586 | K27: 2952.33 | L27: 2954.13 | M27: 2750.52 | N27: 2752.06 | O27: 2752.06 | P27: 76860120000 | R27: 0.079549373 | S27: =(O28-O27)/O27 -> 0.068930183
A28: 43617 | B28: 233.97 | C28: 252.41 | D28: 231.25 | E28: 252.01 | F28: 242.23572 | G28: 25466000 | H28: =(F29-F28)/F28 -> 0.0063721569 | J28: 43617 | K28: 2751.53 | L28: 2964.15 | M28: 2728.81 | N28: 2941.76 | O28: 2941.76 | P28: 70904280000 | R28: 0.0063721569 | S28: =(O29-O28)/O28 -> 0.013128195
A29: 43647 | B29: 253.16 | C29: 258.06 | D29: 249.59 | E29: 252.8 | F29: 243.77928 | G29: 17804000 | H29: =(F30-F29)/F29 -> 0.0044303068 | J29: 43647 | K29: 2971.41 | L29: 3027.98 | M29: 2952.22 | N29: 2980.38 | O29: 2980.38 | P29: 70349470000 | R29: 0.0044303068 | S29: =(O30-O29)/O29 -> -0.018091653
A30: 43678 | B30: 252.89999 | C30: 257.73001 | D30: 229 | E30: 253.92 | F30: 244.8593 | G30: 23570500 | H30: =(F31-F30)/F30 -> -0.0037806242 | J30: 43678 | K30: 2980.32 | L30: 3013.59 | M30: 2822.12 | N30: 2926.46 | O30: 2926.46 | P30: 79599440000 | R30: -0.0037806242 | S30: =(O31-O30)/O30 -> 0.017181168
A31: 43709 | B31: 251.16 | C31: 264.73999 | D31: 245.91 | E31: 252.96001 | F31: 243.93358 | G31: 21646700 | H31: =(F32-F31)/F31 -> 0.015041381 | J31: 43709 | K31: 2909.01 | L31: 3021.99 | M31: 2891.85 | N31: 2976.74 | O31: 2976.74 | P31: 73992330000 | R31: 0.015041381 | S31: =(O32-O31)/O31 -> 0.020431747
A32: 43739 | B32: 254.22 | C32: 259.14999 | D32: 244.09 | E32: 256 | F32: 247.60268 | G32: 23088000 | H32: =(F33-F32)/F32 -> 0.0097657668 | J32: 43739 | K32: 2983.69 | L32: 3050.1 | M32: 2855.94 | N32: 3037.56 | O32: 3037.56 | P32: 77564550000 | R32: 0.0097657668 | S32: =(O33-O32)/O32 -> 0.034047064
A33: 43770 | B33: 257.70001 | C33: 261.69 | D33: 240.61 | E33: 258.5 | F33: 250.02071 | G33: 26774000 | H33: =(F34-F33)/F33 -> 0.052108416 | J33: 43770 | K33: 3050.72 | L33: 3154.26 | M33: 3050.72 | N33: 3140.98 | O33: 3140.98 | P33: 72179920000 | R33: 0.052108416 | S33: =(O34-O33)/O33 -> 0.028589803
A34: 43800 | B34: 258.09 | C34: 275.48001 | D34: 253.58 | E34: 271.97 | F34: 263.04889 | G34: 23036900 | H34: =(F35-F34)/F34 -> 0.014878208 | J34: 43800 | K34: 3143.85 | L34: 3247.93 | M34: 3070.33 | N34: 3230.78 | O34: 3230.78 | P34: 72054000000 | R34: 0.014878208 | S34: =(O35-O34)/O34 -> -0.0016280898
A35: 43831 | B35: 272.09 | C35: 283.95001 | D35: 266.64999 | E35: 275.17999 | F35: 266.96258 | G35: 26915700 | H35: =(F36-F35)/F35 -> -0.13576573 | J35: 43831 | K35: 3244.67 | L35: 3337.77 | M35: 3214.64 | N35: 3225.52 | O35: 3225.52 | P35: 77104420000 | R35: -0.13576573 | S35: =(O36-O35)/O35 -> -0.084110469
A36: 43862 | B36: 277.23001 | C36: 286.72 | D36: 231.61999 | E36: 237.82001 | F36: 230.71822 | G36: 48553900 | H36: =(F37-F36)/F36 -> -0.033849217 | J36: 43862 | K36: 3235.66 | L36: 3393.52 | M36: 2855.84 | N36: 2954.22 | O36: 2954.22 | P36: 84292270000 | R36: -0.033849217 | S36: =(O37-O36)/O36 -> -0.12511932
... A61: 44621 | B61: 271 | C61: 276.48999 | D61: 254.17 | E61: 262.04001 | F61: 261.18014 | G61: 19861800 | H61: =(F62-F61)/F61 -> 0.0032922258 | J61: 44621 | K61: 4363.14 | L61: 4465.4 | M61: 4157.87 | N61: 4463.12 | O61: 4463.12 | P61: 66505140000 | R61: 0.0032922258 | S61: =(O62-O61)/O61 -> 0
A62: 44638 | B62: 261.41 | C62: 262.84 | D62: 257.73999 | E62: 262.04001 | F62: 262.04001 | G62: 2612475 | J62: 44638 | K62: 4407.34 | L62: 4465.4 | M62: 4390.57 | N62: 4463.12 | O62: 4463.12 | P62: 4233761000

Sheet WACC
A1: Total Equity(in millions) | B1: =74621 -> 74621 | D1: weight of equitiy | E1: =B1/(B3+B1) -> 0.80115913
A3: Total Debt(in millions) | B3: 18520.296 | D3: weight of debt | E3: =B3/(B1+B3) -> 0.19884087
A5: Cost of debt | B5: ='Cost of Debt'!H40/100 -> 0.024109514 | D5: DE Ratio | E5: =B3/B1 -> 0.24819148
A7: Cost of Equity | B7: ='Cost of Equity'!X24 -> 0.061305165 | D7: WACC | E7: =WACC!E1*WACC!B7+WACC!B5*WACC!E3*(1-WACC!B9) -> 0.052902418
A9: Tax rate | B9: 0.21 | C9: Assumption 6

Sheet Income Statement
A1: Becton, Dickinson and Company (BDX)
A2: $262.04
A5: Becton, Dickinson and Company
A6: BDX 075887109 2087807 NYSE Common stock
A7: Source: FactSet Fundamentals
B8: SEP '16 | C8: SEP '17 | D8: SEP '18 | E8: SEP '19 | F8: SEP '20 | G8: SEP '21
D10: Restate
A11: Sales | B11: 12483 | C11: 12093 | D11: 15983 | E11: 17290 | F11: 17117 | G11: 20248
A12: Cost of Goods Sold (COGS) incl. D&A | B12: 6492 | C12: 6151 | D12: 8714 | E12: 9002 | F12: 9540 | G12: 10772
A13: COGS excluding D&A | B13: 5442 | C13: 5212 | D13: 6859 | E13: 6872 | F13: 7510 | G13: 8638
A14: Depreciation & Amortization Expense | B14: 1050 | C14: 939 | D14: 1855 | E14: 2130 | F14: 2030 | G14: 2134
A15: Depreciation | B15: 452 | C15: 406 | D15: 600 | E15: 633 | F15: 646 | G15: 731
A16: Amortization of Intangibles | B16: 598 | C16: 533 | D16: 1255 | E16: 1497 | F16: 1384 | G16: 1403
A17: Gross Income | B17: 5991 | C17: 5942 | D17: 7269 | E17: 8288 | F17: 7577 | G17: 9476
A18: SG&A Expense | B18: 3833 | C18: 3699 | D18: 5020 | E18: 5394 | F18: 5421 | G18: 6206
A19: Research & Development | B19: 828 | C19: 774 | D19: 1004 | E19: 1062 | F19: 1096 | G19: 1339
A20: Other SG&A | B20: 3005 | C20: 2925 | D20: 4016 | E20: 4332 | F20: 4325 | G20: 4867
A21: EBIT (Operating Income) | B21: 2158 | C21: 2243 | D21: 2249 | E21: 2894 | F21: 2156 | G21: 3270
A22: Nonoperating Income - Net | B22: 54 | C22: 103 | D22: 400 | E22: -552 | F22: -309 | G22: 229
... A28: Unusual Expense - Net | B28: 731 | C28: 849 | D28: 770 | E28: 527 | F28: 334 | G28: 788
A29: Impairments | G29: 49
A30: Other Intangibles | B30: 0 | C30: 0 | D30: 0 | E30: 0 | F30: 0 | G30: 0
A31: Property,Plant & Equipment | G31: 49
A32: Exceptional Provisions | B32: 0 | C32: 411
A33: Restructuring Expense | B33: 728 | C33: 354 | D33: 740 | E33: 480 | F33: 309 | G33: 185
A34: Legal Claim Expense | G34: 363
A35: Unrealized Valuation Gain/Loss | B35: -3 | C35: -11 | D35: -14 | E35: -23 | F35: -17 | G35: -13
A36: Hedges/Derivatives | B36: -3 | C36: -11 | D36: -14 | E36: -23 | F36: -17 | G36: -13
A37: Excpl Chrgs - Others | C37: 73 | D37: 16 | E37: 24 | F37: 8 | G37: 178
A38: Restructuring of Debt | C38: 73 | D38: 16 | E38: 59 | F38: 8 | G38: 178
A39: Early termination of Contracts costs (Income)
A40: Calamitous Events | D40: 0 | E40: -35 | F40: 0 | G40: 0
A41: Pretax Income | B41: 1074 | C41: 976 | D41: 1173 | E41: 1176 | F41: 985 | G41: 2242
A42: Income Taxes | B42: 98 | C42: -124 | D42: 862 | E42: -57 | F42: 111 | G42: 150
A43: Income Taxes - Current Domestic | B43: 331 | C43: -250 | D43: 737 | E43: 276 | F43: -3 | G43: 148
A44: Income Taxes - Current Foreign | B44: 286 | C44: 200 | D44: 387 | E44: 300 | F44: 400 | G44: 290
A45: Income Taxes - Deferred Domestic | B45: -441 | C45: -64 | D45: -201 | E45: -566 | F45: -185 | G45: -286
A46: Income Taxes - Deferred Foreign | B46: -78 | C46: -10 | D46: -61 | E46: -67 | F46: -101 | G46: -2
A47: Other After Tax Adjustments | B47: 0 | C47: 0 | D47: 0 | E47: 1 | F47: 0 | G47: 0
A48: Consolidated Net Income | B48: 976 | C48: 1100 | D48: 311 | E48: 1234 | F48: 874 | G48: 2092
A49: Net Income | B49: 976 | C49: 1100 | D49: 311 | E49: 1234 | F49: 874 | G49: 2092
A50: Discontinued Operations | B50: 0 | C50: 0 | D50: 0 | E50: 0 | F50: 0 | G50: 0
A51: Preferred Dividends | B51: 0 | C51: 70 | D51: 152 | E51: 152 | F51: 107 | G51: 90
A52: Net Income available to Common | B52: 976 | C52: 1030 | D52: 159 | E52: 1082 | F52: 767 | G52: 2002
A53: Per Share
A54: EPS (recurring) | B54: 6.838868 | C54: 7.264701 | D54: 2.637735 | E54: 5.28032 | F54: 3.543884 | G54: 8.742541
A55: Basic Shares Outstanding | B55: 212.702 | C55: 218.943 | D55: 258.354 | E55: 269.943 | F55: 278.971 | G55: 289.288
A56: Total Shares Outstanding | B56: 213.29123 | C56: 227.9424 | D56: 268.22419 | E56: 270.42732 | F56: 290.01724 | G56: 284.47595
A57: EPS (diluted) | B57: 4.49 | C57: 4.6067 | D57: 0.6 | E57: 3.94 | F57: 2.716 | G57: 6.8541
A58: Diluted Shares Outstanding | B58: 217.536 | C58: 223.588 | D58: 264.621 | E58: 274.775 | F58: 282.402 | G58: 292.089
A59: Total Shares Outstanding | B59: 213.29123 | C59: 227.9424 | D59: 268.22419 | E59: 270.42732 | F59: 290.01724 | G59: 284.47595
A60: Earnings Persistence | B60: 88.731 | C60: 93.648 | D60: 60.553 | E60: 90.815 | F60: 91.888 | G60: 94.873
A61: Dividends per Share | B61: 2.64 | C61: 2.92 | D61: 3 | E61: 3.08 | F61: 3.16 | G61: 3.32
A62: Payout Ratio | B62: 58.797327 | C62: 63.385938 | D62: 500 | E62: 78.172589 | F62: 116.34757 | G62: 48.438161
A63: EBITDA
A64: EBITDA | B64: 3208 | C64: 3182 | D64: 4104 | E64: 5024 | F64: 4186 | G64: 5404
A65: EBIT | B65: 2158 | C65: 2243 | D65: 2249 | E65: 2894 | F65: 2156 | G65: 3270
A66: Depreciation & Amortization Expense | B66: 1050 | C66: 939 | D66: 1855 | E66: 2130 | F66: 2030 | G66: 2134
A67: All figures in millions of U.S. Dollar except per share items.

Sheet Balance Sheet
A1: Becton, Dickinson and Company (BDX)
A2: $262.04
A5: Becton, Dickinson and Company
A6: BDX 075887109 2087807 NYSE Common stock
A7: Source: FactSet Fundamentals
B8: SEP '16 | C8: SEP '17 | D8: SEP '18 | E8: SEP '19 | F8: SEP '20 | G8: SEP '21
D9: Restated
A10: Assets
A11: Cash & Short-Term Investments | B11: 1568 | C11: 14200 | D11: 1253 | E11: 620 | F11: 2937 | G11: 2404
A12: Cash Only | B12: 1541 | C12: 14179 | D12: 1236 | E12: 590 | F12: 2917 | G12: 2392
A13: Total Short Term Investments | B13: 27 | C13: 21 | D13: 17 | E13: 30 | F13: 20 | G13: 12
A14: Short-Term Receivables | B14: 1957 | C14: 1760 | D14: 2319 | E14: 2345 | F14: 2398 | G14: 2497
A15: Accounts Receivables, Net | B15: 1618 | C15: 1744 | D15: 2319 | E15: 2345 | F15: 2398 | G15: 2497
A16: Accounts Receivables, Gross | B16: 1685 | C16: 1793 | D16: 2394 | E16: 2420 | F16: 2478 | G16: 2573
A17: Bad Debt/Doubtful Accounts | B17: -67 | C17: -49 | D17: -75 | E17: -75 | F17: -80 | G17: -76
A18: Other Receivables | B18: 339 | C18: 16 | D18: 0 | E18: 0 | F18: 0 | G18: 0
A19: Inventories | B19: 1719 | C19: 1818 | D19: 2451 | E19: 2579 | F19: 2743 | G19: 2866
A20: Finished Goods | B20: 1129 | C20: 1234 | D20: 1644 | E20: 1717 | F20: 1806 | G20: 1823
A21: Work in Progress | B21: 274 | C21: 271 | D21: 297 | E21: 318 | F21: 335 | G21: 402
A22: Raw Materials | B22: 316 | C22: 313 | D22: 510 | E22: 544 | F22: 602 | G22: 641
... A31: Other Property, Plant & Equipment | B31: 122 | C31: 163 | D31: 183 | E31: 190 | F31: 217 | G31: 240
A32: Operating Lease Right-of-Use Assets | F32: 418 | G32: 446
A33: Accumulated Depreciation | B33: 4518 | C33: 4751 | D33: 5110 | E33: 5469 | F33: 5996 | G33: 6549
A34: Total Long-Term Investments | B34: 796 | C34: 38 | D34: 0 | E34: 0 | F34: 0 | G34: 0
A35: Long-Term Note Receivable | B35: 796 | C35: 38
A36: Intangible Assets | B36: 13770 | C36: 13456 | D36: 40041 | E36: 38354 | F36: 37433 | G36: 36684
A37: Goodwill | B37: 7419 | C37: 7563 | D37: 23600 | E37: 23376 | F37: 23620 | G37: 23901
A38: Other Intangible Assets | B38: 6351 | C38: 5893 | D38: 16441 | E38: 14978 | F38: 13813 | G38: 12783
A39: Deferred Tax Assets | G39: 1343
A40: Other Assets | B40: 752 | C40: 969 | D40: 1077 | E40: 1088 | F40: 1269 | G40: 162
A41: Tangible Other Assets | B41: 752 | C41: 969 | D41: 1077 | E41: 1088 | F41: 1269 | G41: 162
A42: Total Assets | B42: 25586 | C42: 37734 | D42: 53904 | E42: 51765 | F42: 54012 | G42: 53866
A43: Liabilities & Shareholders' Equity
A44: Current
A45: ST Debt & Curr. Portion LT Debt | B45: 1001 | C45: 203 | D45: 2601 | E45: 1309 | F45: 813 | G45: 626
A46: Accounts Payable | B46: 665 | C46: 797 | D46: 1106 | E46: 1092 | F46: 1355 | G46: 1793
A47: Income Tax Payable | B47: 274 | C47: 176 | D47: 343 | E47: 140 | F47: 144 | G47: 176
A48: Other Current Liabilities | B48: 2460 | C48: 2166 | D48: 3166 | E48: 3114 | F48: 3524 | G48: 4031
A49: Accrued Payroll | B49: 696 | C49: 773 | D49: 910 | E49: 987 | F49: 993 | G49: 1214
A50: Miscellaneous Current Liabilities | B50: 1764 | C50: 1393 | D50: 2256 | E50: 2127 | F50: 2531 | G50: 2817
A51: Total Current Liabilities | B51: 4400 | C51: 3342 | D51: 7216 | E51: 5655 | F51: 5836 | G51: 6626
A52: Long-Term
A53: Long-Term Debt | B53: 10550 | C53: 18667 | D53: 18894 | E53: 18081 | F53: 17560 | G53: 17454
A54: Long-Term Debt excl Lease Obligations | B54: 10550 | C54: 18667 | D54: 18894 | E54: 18081 | F54: 17224 | G54: 17110
A55: Capital and Operating Lease Obligations | B55: 0 | C55: 0 | D55: 0 | E55: 0 | F55: 336 | G55: 344
A56: Provision for Risks & Charges | B56: 1319 | C56: 1168 | D56: 1056 | E56: 1272 | F56: 1435 | G56: 1228
A57: Deferred Tax Liabilities | G57: 2693
A58: Other Liabilities | B58: 1684 | C58: 1609 | D58: 5744 | E58: 5676 | F58: 5416 | G58: 2188
A59: Other Liabilities (excl. Deferred Income) | B59: 1684 | C59: 1609 | D59: 5744 | E59: 5676 | F59: 5416 | G59: 2188
A60: Total Liabilities | B60: 17953 | C60: 24786 | D60: 32910 | E60: 30684 | F60: 30247 | G60: 30189
A61: Equity
A62: Preferred Stock (Carrying Value) | B62: 0 | C62: 2 | D62: 2 | E62: 2 | F62: 2 | G62: 2
A63: Non-Redeemable Preferred Stock | B63: 0 | C63: 2 | D63: 2 | E63: 2 | F63: 2 | G63: 2
A64: Common Equity | B64: 7633 | C64: 12946 | D64: 20992 | E64: 21079 | F64: 23763 | G64: 23675
A65: Common Stock Par/Carry Value | B65: 333 | C65: 347 | D65: 347 | E65: 347 | F65: 365 | G65: 365
A66: Additional Paid-In Capital/Capital Surplus | B66: 4693 | C66: 9619 | D66: 16179 | E66: 16270 | F66: 19270 | G66: 19272
A67: Retained Earnings | B67: 12727 | C67: 13109 | D67: 12594 | E67: 12912 | F67: 12791 | G67: 13826
A68: Cumulative Translation Adjustment/Unrealized For. Exch. Gain | B68: -1011 | C68: -1001 | D68: -1162 | E68: -1256 | F68: -1416 | G68: -1294
A69: Unrealized Gain/Loss Marketable Securities | B69: 0 | C69: 0 | D69: 0 | E69: 0 | F69: 0 | G69: 0
A70: Other Appropriated Reserves | B70: -897 | C70: -701 | D70: -723 | E70: -1004 | F70: -1109 | G70: -771
A71: Treasury Stock | B71: -8212 | C71: -8427 | D71: -6243 | E71: -6190 | F71: -6138 | G71: -7723
A72: Total Shareholders' Equity | B72: 7633 | C72: 12948 | D72: 20994 | E72: 21081 | F72: 23765 | G72: 23677
A73: Total Equity | B73: 7633 | C73: 12948 | D73: 20994 | E73: 21081 | F73: 23765 | G73: 23677
A74: Total Liabilities & Shareholders' Equity | B74: 25586 | C74: 37734 | D74: 53904 | E74: 51765 | F74: 54012 | G74: 53866
A75: Per Share
A76: Book Value per Share | B76: 35.78675 | C76: 56.79505 | D76: 78.26289 | E76: 77.947 | F76: 81.93651 | G76: 83.2232
A77: Tangible Book Value per Share | B77: -28.772867 | C77: -2.237407 | D77: -71.018949 | E77: -63.880379 | F77: -47.135128 | G77: -45.7297
A78: All figures in millions of U.S. Dollar except per share items.

Sheet Cash Flow Statement
A1: Becton, Dickinson and Company (BDX)
A2: $262.04
A5: Becton, Dickinson and Company
A6: BDX 075887109 2087807 NYSE Common stock
A7: Source: FactSet Fundamentals
B8: SEP '16 | C8: SEP '17 | D8: SEP '18 | E8: SEP '19 | F8: SEP '20 | G8: SEP '21
D10: Restate
A11: Operating Activities
A12: Net Income / Starting Line | B12: 976 | C12: 1100 | D12: 311 | E12: 1233 | F12: 874 | G12: 2092
A13: Depreciation, Depletion & Amortization | B13: 1114 | C13: 1088 | D13: 1978 | E13: 2253 | F13: 2154 | G13: 2273
A14: Depreciation and Depletion | B14: 516 | C14: 523 | D14: 681 | E14: 712 | F14: 727
A15: Amortization of Intangible Assets | B15: 598 | C15: 565 | D15: 1297 | E15: 1541 | F15: 1427
A16: Deferred Taxes & Investment Tax Credit | B16: -426 | C16: -236 | D16: -240 | E16: -381 | F16: -302 | G16: -304
A17: Deferred Taxes | B17: -426 | C17: -236 | D17: -240 | E17: -381 | F17: -302 | G17: -304
A18: Other Funds | B18: 496 | C18: 969 | D18: -81 | E18: 594 | F18: 700 | G18: 252
A19: Funds from Operations | B19: 2160 | C19: 2921 | D19: 1968 | E19: 3699 | F19: 3426 | G19: 4313
A20: Changes in Working Capital | B20: 399 | C20: -371 | D20: 897 | E20: -369 | F20: 113 | G20: 334
A21: Receivables | B21: -77 | C21: -79 | D21: -170 | E21: -51 | F21: -48 | G21: -95
A22: Inventories | B22: 69 | C22: -46 | D22: 246 | E22: -149 | F22: -125 | G22: -104
A23: Other Assets/Liabilities | B23: 407 | C23: -246 | D23: 821 | E23: -169 | F23: 286 | G23: 533
A24: Net Operating Cash Flow | B24: 2559 | C24: 2550 | D24: 2865 | E24: 3330 | F24: 3539 | G24: 4647
A25: Investing Activities
A26: Capital Expenditures | B26: -718 | C26: -727 | D26: -895 | E26: -957 | F26: -810 | G26: -1231
A27: Capital Expenditures (Fixed Assets) | B27: -693 | C27: -727 | D27: -895 | E27: -957 | F27: -810 | G27: -1231
A28: Capital Expenditures (Other Assets) | B28: -25 | C28: 0 | D28: 0 | E28: 0 | F28: 0 | G28: 0
A29: Net Assets from Acquisitions | B29: 0 | C29: -174 | D29: -15155 | E29: 0 | F29: -164 | G29: -508
A30: Sale of Fixed Assets & Businesses | B30: 158 | C30: 165 | D30: 534 | E30: 477 | F30: 0 | G30: 0
A31: Purchase/Sale of Investments | B31: -1 | C31: 13 | D31: 0 | E31: 0 | F31: 0 | G31: 0
A32: Purchase of Investments | B32: 1 | C32: 0 | D32: 0 | E32: 0 | F32: 0 | G32: 0
A33: Sale/Maturity of Investments | B33: 0 | C33: 13 | D33: 0 | E33: 0 | F33: 0 | G33: 0
A34: Other Funds | B34: -108 | C34: -160 | D34: -217 | E34: -261 | F34: -258 | G34: -142
A35: Other Uses | B35: -108 | C35: -160 | D35: -217 | E35: -261 | F35: -258 | G35: -142
A36: Other Sources | C36: 0 | D36: 0 | E36: 0 | F36: 0 | G36: 0
A37: Net Investing Cash Flow | B37: -669 | C37: -883 | D37: -15733 | E37: -741 | F37: -1232 | G37: -1881
A38: Financing Activities
A39: Cash Dividends Paid | B39: -562 | C39: -677 | D39: -927 | E39: -984 | F39: -1026 | G39: -1048
A40: Common Dividends | B40: -562 | C40: -677 | D40: -927 | E40: -984 | F40: -1026 | G40: -958
A41: Preferred Dividends | B41: 0 | G41: -90
A42: Change in Capital Stock | B42: -32 | C42: 4607 | D42: 0 | E42: 0 | F42: 2917 | G42: -1750
A43: Repurchase of Common & Preferred Stk. | B43: -32 | C43: -220 | D43: 0 | E43: 0 | F43: 0 | G43: -1750
A44: Sale of Common & Preferred Stock | B44: 0 | C44: 4827 | D44: 0 | E44: 0 | F44: 2917 | G44: 0
A45: Proceeds from Sale of Stock | B45: 0 | C45: 4827 | D45: 0 | E45: 0 | F45: 2917 | G45: 0
A46: Issuance/Reduction of Debt, Net | B46: -1252 | C46: 7282 | D46: 1090 | E46: -2035 | F46: -1760 | G46: -243
A47: Change in Current Debt | B47: -500 | C47: -200 | D47: 0 | E47: 485 | F47: -485 | G47: 0
A48: Change in Long-Term Debt | B48: -752 | C48: 7482 | D48: 1090 | E48: -2520 | F48: -1275 | G48: -243
A49: Issuance of Long-Term Debt | B49: 0 | C49: 11462 | D49: 5086 | E49: 2224 | F49: 3389 | G49: 4869
A50: Reduction in Long-Term Debt | B50: -752 | C50: -3980 | D50: -3996 | E50: -4744 | F50: -4664 | G50: -5112
A51: Other Funds | B51: 85 | C51: -235 | D51: -221 | E51: -204 | F51: -109 | G51: -265
A52: Other Uses | B52: 0 | C52: -235 | D52: -221 | E52: -205 | F52: -109 | G52: -265
A53: Other Sources | B53: 85 | C53: 0 | D53: 0 | E53: 1 | F53: 0 | G53: 0
A54: Net Financing Cash Flow | B54: -1761 | C54: 10977 | D54: -58 | E54: -3223 | F54: 22 | G54: -3306
A55: All Activities
A56: Exchange Rate Effect | B56: -12 | C56: -6 | D56: -17 | E56: -12 | F56: -3 | G56: 15
A57: Miscellaneous Funds | B57: 0 | C57: 0 | D57: 0 | E57: 0 | F57: 0 | G57: 0
A58: Net Change in Cash | B58: 117 | C58: 12638 | D58: -12943 | E58: -646 | F58: 2326 | G58: -525
A59: Free Cash Flow | B59: 1866 | C59: 1823 | D59: 1970 | E59: 2373 | F59: 2729 | G59: 3416
A60: Free Cash Flow per Share | B60: 8.577891 | C60: 8.153389 | D60: 7.444609 | E60: 8.636157 | F60: 9.663529 | G60: 11.695066
A61: Free Cash Flow Yield (%) | B61: 4.772654 | C61: 4.160954 | D61: 2.852341 | E61: 3.414041 | F61: 4.153141 | G61: 4.757573
A62: All figures in millions of U.S. Dollar except per share items.

Sheet Segments 
A1: BDX-US
A2: Sales
B3: SEP '12 | C3: SEP '13 | D3: SEP '14 | E3: SEP '15 | F3: SEP '16 | G3: SEP '17 | H3: SEP '18 | I3: SEP '19 | J3: SEP '20 | K3: SEP '21
B4: 366 Days | C4: 365 Days | D4: 365 Days | E4: 365 Days | F4: 366 Days | G4: 365 Days | H4: 365 Days | I4: 365 Days | J4: 366 Days | K4: 365 Days
A5: Total | B5: 7708.382 | C5: 8054 | D5: 8445 | E5: 10282 | F5: 12483 | G5: 12093 | H5: 15983 | I5: 17290 | J5: 17117 | K5: 20248
A6: Medical | B6: 4090.693 | C6: 4306 | D6: 4573 | E6: 6460 | F6: 8654 | G6: 8105 | H6: 8616 | I6: 9064 | J6: 8680 | K6: 9479
A7: Life Sciences | B7: - | C7: - | D7: - | E7: 3822 | F7: 3829 | G7: 3988 | H7: 4330 | I7: 4300 | J7: 4675 | K7: 6530
A8: Interventional | B8: - | C8: - | D8: - | E8: - | F8: - | G8: - | H8: 3037 | I8: 3926 | J8: 3762 | K8: 4239
A9: Historical Segments | B9: 3617.689 | C9: 3748 | D9: 3872 | E9: - | F9: - | G9: - | H9: - | I9: - | J9: - | K9: -
A10: Diagnostics | B10: 2538.055 | C10: 2646 | D10: 2713 | E10: - | F10: - | G10: - | H10: - | I10: - | J10: - | K10: -
A11: Biosciences | B11: 1079.634 | C11: 1102 | D11: 1159 | E11: - | F11: - | G11: - | H11: - | I11: - | J11: - | K11: -
A12: All figures in millions of U.S. Dollar
